{"days":{"images":{"size":5340161183,"files":[{"id":"e8390218-0915-474c-be19-43b5a8952874","file":"DSC_9214.jpg","width":"3822","height":"5809","date":"2023:09:30 18:51:59","thumbnail":null,"size":7164141},{"id":"6331f692-8d41-41e4-8685-7977b51dbb26","file":"DSC_9213.jpg","width":"3822","height":"5809","date":"2023:09:30 18:51:58","thumbnail":null,"size":7342544},{"id":"84504566-66c4-48f5-974b-f55294f20319","file":"DSC_9212.jpg","width":"3822","height":"5809","date":"2023:09:30 18:51:57","thumbnail":null,"size":6995754},{"id":"35f02dac-7490-42be-9bad-9d5f69b95431","file":"DSC_9211.jpg","width":"3822","height":"5809","date":"2023:09:30 18:51:55","thumbnail":null,"size":7014859},{"id":"14dccb52-dee4-4fe9-80fb-6279058b635f","file":"DSC_9209.jpg","width":"3822","height":"5809","date":"2023:09:30 18:51:37","thumbnail":null,"size":26226134},{"id":"0c8c0fda-a88c-456d-bd24-4800f6d97c23","file":"DSC_9210.jpg","width":"3822","height":"5809","date":"2023:09:30 18:51:37","thumbnail":null,"size":26379550},{"id":"b538eeca-89bd-41dd-8253-dd097310ccd9","file":"DSC_9208.jpg","width":"3822","height":"5809","date":"2023:09:30 18:51:36","thumbnail":null,"size":24935741},{"id":"1c3ab1d2-768a-4865-a33f-d3425c02b35a","file":"DSC_9207.jpg","width":"3822","height":"5809","date":"2023:09:30 18:51:31","thumbnail":null,"size":25064955},{"id":"c55ed977-1650-48fc-a0e9-0d16bf66240a","file":"DSC_9206.jpg","width":"3822","height":"5809","date":"2023:09:30 18:51:28","thumbnail":null,"size":28551006},{"id":"d0fb00f3-0d3e-481c-bdf4-88b92082064e","file":"DSC_9203.jpg","width":"3822","height":"5809","date":"2023:09:30 18:47:05","thumbnail":null,"size":23852101},{"id":"985892e1-8ff7-4b44-9c14-b4f7f54cfc5b","file":"DSC_9204.jpg","width":"3822","height":"5809","date":"2023:09:30 18:47:05","thumbnail":null,"size":23641682},{"id":"edb91111-9161-4505-a770-fb6d5e27ee5a","file":"DSC_9201.jpg","width":"3822","height":"5809","date":"2023:09:30 18:47:04","thumbnail":null,"size":20389378},{"id":"41d2279e-02b5-4d47-b24d-8dc9474479c3","file":"DSC_9202.jpg","width":"3822","height":"5809","date":"2023:09:30 18:47:04","thumbnail":null,"size":23527226},{"id":"47741e55-da95-40d3-916e-ed88588bf572","file":"DSC_9199.jpg","width":"5809","height":"3822","date":"2023:09:30 18:40:29","thumbnail":null,"size":7888747},{"id":"63af9e76-280e-46e2-898c-d06d27ac014f","file":"DSC_9200.jpg","width":"5809","height":"3822","date":"2023:09:30 18:40:29","thumbnail":null,"size":7776163},{"id":"51a0df31-74d9-436a-ace7-fdcec914a630","file":"DSC_9198.jpg","width":"5809","height":"3822","date":"2023:09:30 18:40:26","thumbnail":null,"size":9387348},{"id":"424b7d6a-80db-477a-927f-ff8c0cea60af","file":"DSC_9196.jpg","width":"3822","height":"5809","date":"2023:09:30 18:36:35","thumbnail":null,"size":25432614},{"id":"c45b2892-1bea-4ed5-8d7f-2a150a683000","file":"DSC_9197.jpg","width":"3822","height":"5809","date":"2023:09:30 18:36:35","thumbnail":null,"size":25604352},{"id":"7d1edcbc-30c3-4e5d-8d82-b6abeac3281c","file":"DSC_9195.jpg","width":"3822","height":"5809","date":"2023:09:30 18:36:34","thumbnail":null,"size":18804578},{"id":"f2bd2283-a7c9-49c2-b250-2e4dc6113624","file":"DSC_9194.jpg","width":"3822","height":"5809","date":"2023:09:30 18:35:51","thumbnail":null,"size":25051953},{"id":"5fb405bd-7aec-4795-ac1b-6d7724d2ef56","file":"DSC_9193.jpg","width":"3822","height":"5809","date":"2023:09:30 18:35:50","thumbnail":null,"size":24846090},{"id":"c111e2b7-43db-4760-9ec1-5e711b1a428c","file":"DSC_9192.jpg","width":"3822","height":"5809","date":"2023:09:30 18:35:49","thumbnail":null,"size":28181717},{"id":"57fd2084-755d-445e-aeab-68d156fe70e0","file":"DSC_9190.jpg","width":"3822","height":"5809","date":"2023:09:30 18:34:27","thumbnail":null,"size":18416166},{"id":"150239cb-381a-4835-8f5e-262c1a6b67c9","file":"DSC_9191.jpg","width":"3822","height":"5809","date":"2023:09:30 18:34:27","thumbnail":null,"size":24821936},{"id":"d0ddc00b-e902-4517-9f96-a464f9c4bbc8","file":"DSC_9189.jpg","width":"3822","height":"5809","date":"2023:09:30 18:34:26","thumbnail":null,"size":8914822},{"id":"ebdc1091-c2cf-4a21-bd93-f8ab1fed33ec","file":"DSC_9188.jpg","width":"3822","height":"5809","date":"2023:09:30 18:34:25","thumbnail":null,"size":28496674},{"id":"33c1631c-a8e7-49a7-9f68-f6b4bb6ff2bc","file":"DSC_9187.jpg","width":"3822","height":"5809","date":"2023:09:30 18:34:24","thumbnail":null,"size":25355638},{"id":"0ead7f44-a1c8-4f27-a494-444ee402e317","file":"DSC_9185.jpg","width":"3822","height":"5809","date":"2023:09:30 18:34:23","thumbnail":null,"size":25152708},{"id":"3c8f2b91-2829-403b-878b-0959714b8ec0","file":"DSC_9186.jpg","width":"3822","height":"5809","date":"2023:09:30 18:34:23","thumbnail":null,"size":25633291},{"id":"64309d3b-17e1-4663-a33f-402ad9cd784a","file":"DSC_9183.jpg","width":"3822","height":"5809","date":"2023:09:30 18:34:08","thumbnail":null,"size":20838459},{"id":"3aee1640-4a16-41c2-afc4-c7128bca448e","file":"DSC_9184.jpg","width":"3822","height":"5809","date":"2023:09:30 18:34:08","thumbnail":null,"size":19040642},{"id":"4c4b216f-0b23-490a-9854-d9a207557d5c","file":"DSC_9182.jpg","width":"3822","height":"5809","date":"2023:09:30 18:32:55","thumbnail":null,"size":27859785},{"id":"ffd7e773-73f4-452b-9b6c-92767d5e4678","file":"DSC_9181.jpg","width":"3822","height":"5809","date":"2023:09:30 18:32:43","thumbnail":null,"size":27653978},{"id":"7a2ccc1e-28b2-4ed1-9678-6963ccf6ac17","file":"DSC_9180.jpg","width":"3822","height":"5809","date":"2023:09:30 18:32:42","thumbnail":null,"size":22127603},{"id":"a430da04-f787-4e86-8c2b-91820eae7b81","file":"DSC_9179.jpg","width":"3822","height":"5809","date":"2023:09:30 18:32:35","thumbnail":null,"size":30711552},{"id":"672daded-8351-4a15-b41d-995625c9b95a","file":"DSC_9178.jpg","width":"3822","height":"5809","date":"2023:09:30 18:32:15","thumbnail":null,"size":21194405},{"id":"249cf751-1d38-4afa-9257-8b43df649d8a","file":"DSC_9177.jpg","width":"3822","height":"5809","date":"2023:09:30 18:32:12","thumbnail":null,"size":22107347},{"id":"4a16dd55-df57-40d0-be35-c7260b75b942","file":"DSC_9176.jpg","width":"3822","height":"5809","date":"2023:09:30 18:32:11","thumbnail":null,"size":18114957},{"id":"b5d8728c-5737-41ea-b2e6-b76a1e1c36f7","file":"DSC_9175.jpg","width":"5809","height":"3822","date":"2023:09:30 18:32:04","thumbnail":null,"size":6975278},{"id":"18e6e42a-138f-450f-8526-bdc63a46b2bd","file":"DSC_9174.jpg","width":"5809","height":"3822","date":"2023:09:30 18:32:03","thumbnail":null,"size":7450144},{"id":"453a09f5-9f09-42e4-a6a4-a09745308790","file":"DSC_9173.jpg","width":"5809","height":"3822","date":"2023:09:30 18:32:02","thumbnail":null,"size":6725308},{"id":"a685c16f-5de5-4d1e-8ce2-00c41a6026ca","file":"DSC_9172.jpg","width":"3822","height":"5809","date":"2023:09:30 18:31:55","thumbnail":null,"size":8131609},{"id":"87049707-aeb0-44a8-8cd9-b679050bcabc","file":"DSC_9171.jpg","width":"3822","height":"5809","date":"2023:09:30 18:31:50","thumbnail":null,"size":7199299},{"id":"0abc117a-9f82-4ab1-a7fb-3382087a4d0c","file":"DSC_9170.jpg","width":"3822","height":"5809","date":"2023:09:30 18:31:49","thumbnail":null,"size":7776332},{"id":"a15a4064-fb3e-4e93-8dad-0397f91e3cf3","file":"DSC_9168.jpg","width":"3822","height":"5809","date":"2023:09:30 18:31:21","thumbnail":null,"size":29377701},{"id":"a91f0691-3fcc-4ac5-bcf5-565296374659","file":"DSC_9169.jpg","width":"3822","height":"5809","date":"2023:09:30 18:31:21","thumbnail":null,"size":29217810},{"id":"d5901a84-84dc-4c92-a157-af388fffc756","file":"DSC_9167.jpg","width":"3822","height":"5809","date":"2023:09:30 18:31:20","thumbnail":null,"size":27137903},{"id":"9744d259-3069-4a52-959c-c95dd39a1ae1","file":"DSC_9166.jpg","width":"3822","height":"5809","date":"2023:09:30 18:31:18","thumbnail":null,"size":28886759},{"id":"cb608895-f7c1-40e7-b016-28ce2007f2b1","file":"DSC_9164.jpg","width":"5809","height":"3822","date":"2023:09:30 18:29:03","thumbnail":null,"size":19542974},{"id":"b6bf21ea-e417-4811-ac0f-b198f3fb0aa6","file":"DSC_9163.jpg","width":"5809","height":"3822","date":"2023:09:30 18:28:59","thumbnail":null,"size":13602040},{"id":"4152ab27-ae94-4486-b61b-ad4c149aea42","file":"DSC_9162.jpg","width":"3822","height":"5809","date":"2023:09:30 18:28:48","thumbnail":null,"size":10553500},{"id":"9a82924f-7732-4e67-9e51-8349de52d7a8","file":"DSC_9161.jpg","width":"3822","height":"5809","date":"2023:09:30 18:28:45","thumbnail":null,"size":11974129},{"id":"c01bd44c-8615-4521-af57-b04030fdbbbd","file":"DSC_9160.jpg","width":"5809","height":"3822","date":"2023:09:30 18:28:33","thumbnail":null,"size":7163884},{"id":"eb280abe-91c4-4b1a-a5bd-ae0c07ea8eae","file":"DSC_9159.jpg","width":"5809","height":"3822","date":"2023:09:30 18:28:32","thumbnail":null,"size":5181285},{"id":"e3ae0707-7d1c-4545-9313-a2414e1e29f9","file":"DSC_9158.jpg","width":"5809","height":"3822","date":"2023:09:30 18:28:31","thumbnail":null,"size":6709669},{"id":"b9d39626-1893-4b6a-a352-6860b540f572","file":"DSC_9157.jpg","width":"3822","height":"5809","date":"2023:09:30 18:28:24","thumbnail":null,"size":7122112},{"id":"68a2282b-5f59-4cd7-826e-5729ee298275","file":"DSC_9156.jpg","width":"3822","height":"5809","date":"2023:09:30 18:28:23","thumbnail":null,"size":12130330},{"id":"eaff8608-1448-46d7-a8cb-984334ea1d73","file":"DSC_9155.jpg","width":"3822","height":"5809","date":"2023:09:30 18:28:19","thumbnail":null,"size":16049201},{"id":"ff2152ec-5af3-4e88-8f32-e8be9d2a50d7","file":"DSC_9154.jpg","width":"3822","height":"5809","date":"2023:09:30 18:28:18","thumbnail":null,"size":15277858},{"id":"63e7108f-f9f9-4715-8af1-fe62f6f836c7","file":"DSC_9152.jpg","width":"3822","height":"5809","date":"2023:09:30 18:28:17","thumbnail":null,"size":15822808},{"id":"879c8dcd-2e49-4b09-8cb9-3c3773b2e623","file":"DSC_9153.jpg","width":"3822","height":"5809","date":"2023:09:30 18:28:17","thumbnail":null,"size":17085785},{"id":"1d890215-1791-4773-aa4f-2c85f68fad2c","file":"DSC_9151.jpg","width":"3822","height":"5809","date":"2023:09:30 18:28:14","thumbnail":null,"size":15560052},{"id":"9967ea59-99e0-4ed2-9d08-db6f7eee34a7","file":"DSC_9150.jpg","width":"3822","height":"5809","date":"2023:09:30 18:28:09","thumbnail":null,"size":21377124},{"id":"c43b926f-fbe3-4173-a696-fc1448d373d1","file":"DSC_9149.jpg","width":"3822","height":"5809","date":"2023:09:30 18:27:54","thumbnail":null,"size":30811043},{"id":"1343ddf6-3e34-49ef-b8cc-2fcbfdc77732","file":"DSC_9148.jpg","width":"3822","height":"5809","date":"2023:09:30 18:26:22","thumbnail":null,"size":19973620},{"id":"f7dac721-1480-4fa1-a317-2f60513ea6ac","file":"DSC_9147.jpg","width":"3822","height":"5809","date":"2023:09:30 18:26:21","thumbnail":null,"size":25057412},{"id":"82a2ed2a-cbe4-4eff-bdbf-e6e602db413f","file":"DSC_9146.jpg","width":"3822","height":"5809","date":"2023:09:30 18:26:18","thumbnail":null,"size":27168146},{"id":"b4c7801f-2b11-4bc1-904e-c57890fb8f76","file":"DSC_9145.jpg","width":"3822","height":"5809","date":"2023:09:30 18:26:17","thumbnail":null,"size":25086856},{"id":"544007da-ccaf-4cfb-ae65-4eb1a7549c7e","file":"DSC_9144.jpg","width":"3822","height":"5809","date":"2023:09:30 18:25:18","thumbnail":null,"size":25325082},{"id":"fe156dbd-ca1a-4ef9-9939-48ea6dafff33","file":"DSC_9143.jpg","width":"3822","height":"5809","date":"2023:09:30 18:25:16","thumbnail":null,"size":24915501},{"id":"fce24f62-568f-4e3a-bfd1-4234238b3cc0","file":"DSC_9141.jpg","width":"5809","height":"3822","date":"2023:09:30 18:13:32","thumbnail":null,"size":6363503},{"id":"e734d8cf-b8ba-4e55-ade0-b5a7a2815bb3","file":"DSC_9142.jpg","width":"5809","height":"3822","date":"2023:09:30 18:13:32","thumbnail":null,"size":6095431},{"id":"b56beb67-7f9c-428e-9cfa-69617d781e36","file":"DSC_9140.jpg","width":"5809","height":"3822","date":"2023:09:30 18:13:31","thumbnail":null,"size":6930472},{"id":"fab9eca6-30ca-4dd0-aa91-e39ec367d44c","file":"DSC_9139.jpg","width":"5809","height":"3822","date":"2023:09:30 18:13:30","thumbnail":null,"size":6992294},{"id":"e8a90538-3c44-4864-987c-31fb9b19ff5d","file":"DSC_9138.jpg","width":"5809","height":"3822","date":"2023:09:30 18:13:20","thumbnail":null,"size":6712112},{"id":"e85901b8-ca9f-4887-b266-12683929c5c0","file":"DSC_9137.jpg","width":"5809","height":"3822","date":"2023:09:30 18:13:00","thumbnail":null,"size":7434460},{"id":"73f73dcd-7da0-4743-89b4-ebd19d6e6ac1","file":"DSC_9136.jpg","width":"5809","height":"3822","date":"2023:09:30 18:12:13","thumbnail":null,"size":6262074},{"id":"b62d6605-6468-41f5-8935-9c62dbb39d7d","file":"DSC_9135.jpg","width":"5809","height":"3822","date":"2023:09:30 18:12:12","thumbnail":null,"size":6144494},{"id":"faf5a86b-09a3-487b-88ef-0638ef218371","file":"DSC_9133.jpg","width":"5809","height":"3822","date":"2023:09:30 18:12:01","thumbnail":null,"size":6294720},{"id":"caa82ebd-ed9f-477b-af42-eaad5b53cb8d","file":"DSC_9132.jpg","width":"5809","height":"3822","date":"2023:09:30 18:12:00","thumbnail":null,"size":6316980},{"id":"976a7911-4552-4f3d-9a87-14661e1bd534","file":"DSC_9131.jpg","width":"5809","height":"3822","date":"2023:09:30 18:11:56","thumbnail":null,"size":6236502},{"id":"6658b2dc-b393-4acc-bee6-9c29a45553ef","file":"DSC_9130.jpg","width":"3822","height":"5809","date":"2023:09:30 18:11:15","thumbnail":null,"size":9089050},{"id":"1d949252-e8a2-42ae-8d81-ab2944bc9c37","file":"DSC_9129.jpg","width":"3822","height":"5809","date":"2023:09:30 18:11:12","thumbnail":null,"size":9821814},{"id":"da196ce5-440f-4fc6-bd5a-506fcd4fcce0","file":"DSC_9128.jpg","width":"3822","height":"5809","date":"2023:09:30 18:10:03","thumbnail":null,"size":8585261},{"id":"ca3b09ed-bd18-41a7-8fd2-5061fc43eea9","file":"DSC_9127.jpg","width":"3822","height":"5809","date":"2023:09:30 18:10:01","thumbnail":null,"size":8979636},{"id":"8e55a656-9ee3-44df-8cb1-5571b2c0f958","file":"DSC_9126.jpg","width":"3822","height":"5809","date":"2023:09:30 18:09:58","thumbnail":null,"size":8809091},{"id":"16e7e90c-a627-4d3d-b5de-72fdd67f48ed","file":"DSC_9125.jpg","width":"3822","height":"5809","date":"2023:09:30 18:09:55","thumbnail":null,"size":9132703},{"id":"2c11b721-b596-4622-9846-92a02f8c2601","file":"DSC_9123.jpg","width":"3822","height":"5809","date":"2023:09:30 18:09:31","thumbnail":null,"size":9515466},{"id":"40c04e0e-1694-4e9a-a9ce-55364d556ceb","file":"DSC_9124.jpg","width":"3822","height":"5809","date":"2023:09:30 18:09:31","thumbnail":null,"size":9841248},{"id":"1948c1a5-0156-4016-b938-33821f6008d4","file":"DSC_9122.jpg","width":"3822","height":"5809","date":"2023:09:30 18:09:30","thumbnail":null,"size":8990099},{"id":"e490a1b1-060e-4818-be3b-129bb09c5293","file":"DSC_9121.jpg","width":"3822","height":"5809","date":"2023:09:30 18:09:21","thumbnail":null,"size":9784230},{"id":"c998d9de-9405-48fb-aac6-31f856138fd8","file":"DSC_9120.jpg","width":"3822","height":"5809","date":"2023:09:30 18:09:09","thumbnail":null,"size":8459272},{"id":"074015d0-7758-48c1-95c1-4506dd82d3cf","file":"DSC_9119.jpg","width":"3822","height":"5809","date":"2023:09:30 18:09:08","thumbnail":null,"size":8340550},{"id":"88647cc3-a9c7-48ca-ba72-ea7997730412","file":"DSC_9118.jpg","width":"3822","height":"5809","date":"2023:09:30 18:09:04","thumbnail":null,"size":7784033},{"id":"bf927a0c-6e40-4357-97a4-dadc9d3d43a4","file":"DSC_9117.jpg","width":"3822","height":"5809","date":"2023:09:30 18:09:03","thumbnail":null,"size":9573967},{"id":"8ba3f4c6-7f78-45b8-8228-30d48dd5b5e6","file":"DSC_9116.jpg","width":"3822","height":"5809","date":"2023:09:30 18:08:43","thumbnail":null,"size":7162696},{"id":"7f2ccc7c-a4aa-4db2-8d46-13bae7ea18f8","file":"DSC_9115.jpg","width":"3822","height":"5809","date":"2023:09:30 18:08:42","thumbnail":null,"size":7254128},{"id":"9dce0643-dc00-4522-bd0c-04faf08c9463","file":"DSC_9114.jpg","width":"3822","height":"5809","date":"2023:09:30 18:04:57","thumbnail":null,"size":9646431},{"id":"df5cb265-d2ae-471d-b7e9-61ab90ef36a1","file":"DSC_9112.jpg","width":"3822","height":"5809","date":"2023:09:30 18:04:46","thumbnail":null,"size":8338547},{"id":"afd4b792-5357-4964-a5e9-b4f1ad2643fc","file":"DSC_9113.jpg","width":"3822","height":"5809","date":"2023:09:30 18:04:46","thumbnail":null,"size":8230521},{"id":"9bdbfeb7-3d8c-41a0-92b8-cbdffb1c8865","file":"DSC_9111.jpg","width":"3822","height":"5809","date":"2023:09:30 18:04:45","thumbnail":null,"size":7853382},{"id":"fd99e6e6-1bf5-4717-927b-b60112a24b07","file":"DSC_9110.jpg","width":"3822","height":"5809","date":"2023:09:30 18:04:43","thumbnail":null,"size":8353907},{"id":"cf14c5ff-4b70-45a7-8545-17c61a10fde4","file":"DSC_9109.jpg","width":"3822","height":"5809","date":"2023:09:30 18:04:39","thumbnail":null,"size":8233676},{"id":"c0b78333-8582-470a-9313-ae721cb1b053","file":"DSC_9107.jpg","width":"3822","height":"5809","date":"2023:09:30 18:04:02","thumbnail":null,"size":8746977},{"id":"c306b30e-091b-493b-acac-619ca5659594","file":"DSC_9106.jpg","width":"3822","height":"5809","date":"2023:09:30 18:04:00","thumbnail":null,"size":8418207},{"id":"7e36d84d-d699-491f-b956-11f338c8bba4","file":"DSC_9105.jpg","width":"3822","height":"5809","date":"2023:09:30 18:03:58","thumbnail":null,"size":8130004},{"id":"0b02cb55-7db1-408e-9b66-d849be75cfd5","file":"DSC_9103.jpg","width":"3822","height":"5809","date":"2023:09:30 18:03:44","thumbnail":null,"size":7089811},{"id":"f03e9845-c4c4-4ced-9fa4-d69e4a2588e0","file":"DSC_9104.jpg","width":"3822","height":"5809","date":"2023:09:30 18:03:44","thumbnail":null,"size":6975294},{"id":"380d8667-b80f-4654-9e44-df85d8218fd7","file":"DSC_9102.jpg","width":"3822","height":"5809","date":"2023:09:30 18:03:43","thumbnail":null,"size":7135674},{"id":"473e5e8a-1f55-4e1a-aefd-29eef919a553","file":"DSC_9101.jpg","width":"3822","height":"5809","date":"2023:09:30 18:03:37","thumbnail":null,"size":6824856},{"id":"f57705c7-e2ae-41af-80c8-84dea79d8ad6","file":"DSC_9099.jpg","width":"3822","height":"5809","date":"2023:09:30 18:03:36","thumbnail":null,"size":6647237},{"id":"a1c905e5-6c7a-472f-bbde-e193be58149d","file":"DSC_9100.jpg","width":"3822","height":"5809","date":"2023:09:30 18:03:36","thumbnail":null,"size":6945947},{"id":"b1cc4941-1a85-46b9-b795-c946ad010d94","file":"DSC_9098.jpg","width":"3822","height":"5809","date":"2023:09:30 18:02:16","thumbnail":null,"size":11620155},{"id":"04e6faa6-5a2c-4091-b30a-d13072ad170f","file":"DSC_9096.jpg","width":"3822","height":"5809","date":"2023:09:30 18:01:27","thumbnail":null,"size":16703852},{"id":"8896a6a3-959e-4e6f-ad90-1fa0d674fb4a","file":"DSC_9097.jpg","width":"3822","height":"5809","date":"2023:09:30 18:01:27","thumbnail":null,"size":16450794},{"id":"7bffd3c4-a7b5-4436-817b-58de3344b035","file":"DSC_9095.jpg","width":"3822","height":"5809","date":"2023:09:30 18:01:26","thumbnail":null,"size":15969700},{"id":"5dc26860-6c2d-48a6-bf48-c689ff667ea6","file":"DSC_9094.jpg","width":"3822","height":"5809","date":"2023:09:30 18:01:12","thumbnail":null,"size":6864938},{"id":"10ceb46f-2e1d-4c86-bc5b-f514ae1923b4","file":"DSC_9093.jpg","width":"3822","height":"5809","date":"2023:09:30 18:01:11","thumbnail":null,"size":6903290},{"id":"429309d1-d91c-4ca6-8777-ac6130bdf1b6","file":"DSC_9092.jpg","width":"3822","height":"5809","date":"2023:09:30 18:00:53","thumbnail":null,"size":13718928},{"id":"d3d40a6d-9b81-44f8-8c9a-edc0b07de686","file":"DSC_9091.jpg","width":"3822","height":"5809","date":"2023:09:30 18:00:51","thumbnail":null,"size":14095719},{"id":"324cdc98-d7a0-48ac-9379-5bff532713c3","file":"DSC_9090.jpg","width":"3822","height":"5809","date":"2023:09:30 18:00:24","thumbnail":null,"size":9734159},{"id":"3b161618-5c54-411b-bfe1-7993aadba915","file":"DSC_9089.jpg","width":"3822","height":"5809","date":"2023:09:30 17:58:31","thumbnail":null,"size":15551376},{"id":"451b06a7-846b-4bae-80e1-d2a620bb0771","file":"DSC_9088.jpg","width":"3822","height":"5809","date":"2023:09:30 17:58:26","thumbnail":null,"size":16838199},{"id":"e91be48f-a152-4a2d-9db8-fd726fb16d21","file":"DSC_9087.jpg","width":"3822","height":"5809","date":"2023:09:30 17:58:18","thumbnail":null,"size":14909335},{"id":"6fa3cc37-d32e-404d-a377-977090c3553c","file":"DSC_9086.jpg","width":"3822","height":"5809","date":"2023:09:30 17:58:17","thumbnail":null,"size":14684879},{"id":"58eecb43-ef31-4e86-bac4-814fe542f60c","file":"DSC_9085.jpg","width":"3822","height":"5809","date":"2023:09:30 17:58:15","thumbnail":null,"size":15738802},{"id":"40ade070-fda2-4ef3-9bb8-ccbf268793bb","file":"DSC_9084.jpg","width":"3822","height":"5809","date":"2023:09:30 17:57:08","thumbnail":null,"size":27958728},{"id":"89df83c0-b9fb-43c3-9577-b4a927a7c09b","file":"DSC_9082.jpg","width":"3822","height":"5809","date":"2023:09:30 17:57:07","thumbnail":null,"size":28925649},{"id":"ffaa44ba-73c6-4346-b7d4-d15ba413d0dc","file":"DSC_9083.jpg","width":"3822","height":"5809","date":"2023:09:30 17:57:07","thumbnail":null,"size":28680362},{"id":"63a8d9e5-859c-4cb7-9180-d8ec027f35cc","file":"DSC_9081.jpg","width":"3822","height":"5809","date":"2023:09:30 17:57:06","thumbnail":null,"size":29695693},{"id":"d85b85c5-90ee-4ea1-8870-6e8e1b306fa5","file":"DSC_9080.jpg","width":"5809","height":"3822","date":"2023:09:30 17:56:01","thumbnail":null,"size":20993371},{"id":"18bd032a-982a-41d4-95d8-784d3a648f60","file":"DSC_9078.jpg","width":"3822","height":"5809","date":"2023:09:30 17:55:30","thumbnail":null,"size":24354083},{"id":"5635b1c2-5733-4afe-bf00-594215432c8f","file":"DSC_9077.jpg","width":"3822","height":"5809","date":"2023:09:30 17:55:28","thumbnail":null,"size":24411995},{"id":"c51bbfa3-eae1-4634-a6ee-b0d9db5b8f72","file":"DSC_9076.jpg","width":"3822","height":"5809","date":"2023:09:30 17:55:18","thumbnail":null,"size":22737527},{"id":"a2747917-f7bf-45e5-b8b1-19505e5d883e","file":"DSC_9075.jpg","width":"3822","height":"5809","date":"2023:09:30 17:54:47","thumbnail":null,"size":8300336},{"id":"ae6fbee0-6f54-4f31-8137-1ab3b327e453","file":"DSC_9074.jpg","width":"3822","height":"5809","date":"2023:09:30 17:54:46","thumbnail":null,"size":8083944},{"id":"2f48635c-3398-4e1e-bd4e-11cba82668a1","file":"DSC_9073.jpg","width":"3822","height":"5809","date":"2023:09:30 17:54:38","thumbnail":null,"size":8138246},{"id":"3c7c06e9-6b34-4a78-8aeb-412dc115c69e","file":"DSC_9071.jpg","width":"3822","height":"5809","date":"2023:09:30 17:54:37","thumbnail":null,"size":8122716},{"id":"0913aa79-7f63-44fc-8364-4d620c589b38","file":"DSC_9072.jpg","width":"3822","height":"5809","date":"2023:09:30 17:54:37","thumbnail":null,"size":8120896},{"id":"d5d026a1-6e64-481a-aeba-39d92f172c40","file":"DSC_9070.jpg","width":"3822","height":"5809","date":"2023:09:30 17:54:14","thumbnail":null,"size":25846589},{"id":"fe0ad02a-3a7b-4f4f-bae6-d729ca18464b","file":"DSC_9068.jpg","width":"3822","height":"5809","date":"2023:09:30 17:54:13","thumbnail":null,"size":18933230},{"id":"12e39b60-07e3-45a6-9e99-b7889e850ef2","file":"DSC_9069.jpg","width":"3822","height":"5809","date":"2023:09:30 17:54:13","thumbnail":null,"size":26309538},{"id":"b5044ec8-adc5-4b5a-b39e-b1dc617d4255","file":"DSC_9067.jpg","width":"3822","height":"5809","date":"2023:09:30 17:54:11","thumbnail":null,"size":21776103},{"id":"7acce488-1503-4eb2-be83-d9eac1899a95","file":"DSC_9066.jpg","width":"3822","height":"5809","date":"2023:09:30 17:53:56","thumbnail":null,"size":8203361},{"id":"9517fe79-71ab-4947-b709-e3c6988cac6c","file":"DSC_9064.jpg","width":"3822","height":"5809","date":"2023:09:30 17:53:20","thumbnail":null,"size":7819623},{"id":"510b3fd9-015e-45f2-bbda-91f768605f05","file":"DSC_9062.jpg","width":"3822","height":"5809","date":"2023:09:30 17:53:19","thumbnail":null,"size":7249380},{"id":"79bf499d-80d6-4e58-9631-1ec8cc6150b3","file":"DSC_9063.jpg","width":"3822","height":"5809","date":"2023:09:30 17:53:19","thumbnail":null,"size":7471446},{"id":"6a2b9cd7-b390-43ea-ac15-07a16d52291c","file":"DSC_9061.jpg","width":"3822","height":"5809","date":"2023:09:30 17:53:17","thumbnail":null,"size":7295823},{"id":"2dccc807-d0c4-4fb2-bef8-03ffbf452b2a","file":"DSC_9060.jpg","width":"5809","height":"3822","date":"2023:09:30 17:53:12","thumbnail":null,"size":7128718},{"id":"72d43ab5-c132-41e5-962f-47207268b33f","file":"DSC_9059.jpg","width":"5809","height":"3822","date":"2023:09:30 17:53:08","thumbnail":null,"size":7118137},{"id":"338acd77-e85c-4578-a7b8-1a0b86e8517b","file":"DSC_9058.jpg","width":"5809","height":"3822","date":"2023:09:30 17:53:05","thumbnail":null,"size":6617686},{"id":"8de0f3b2-f943-410d-897e-0564dedfaeb4","file":"DSC_9056.jpg","width":"3822","height":"5809","date":"2023:09:30 17:53:00","thumbnail":null,"size":7806642},{"id":"c9320f29-c1c9-4be9-860e-799dee1b2abd","file":"DSC_9057.jpg","width":"3822","height":"5809","date":"2023:09:30 17:53:00","thumbnail":null,"size":7708896},{"id":"12f2a879-5328-43da-983d-da1e01d354f2","file":"DSC_9053.jpg","width":"3822","height":"5809","date":"2023:09:30 17:52:59","thumbnail":null,"size":7894676},{"id":"e0240d0e-58f1-423e-98fb-52b75cb5ff2d","file":"DSC_9054.jpg","width":"3822","height":"5809","date":"2023:09:30 17:52:59","thumbnail":null,"size":7823014},{"id":"c198390e-3c1c-4a9f-b96a-1a935a45726f","file":"DSC_9055.jpg","width":"3822","height":"5809","date":"2023:09:30 17:52:59","thumbnail":null,"size":7858169},{"id":"2d46eae3-72d2-4ee9-a622-6fe9eb796948","file":"DSC_9052.jpg","width":"3822","height":"5809","date":"2023:09:30 17:52:58","thumbnail":null,"size":6019542},{"id":"a6398cf2-b818-4850-82e2-9cb40c05dc7f","file":"DSC_9050.jpg","width":"3822","height":"5809","date":"2023:09:30 17:51:52","thumbnail":null,"size":35816792},{"id":"98d3fc67-34a7-4a62-9e52-dac8420243a3","file":"DSC_9048.jpg","width":"3822","height":"5809","date":"2023:09:30 17:51:10","thumbnail":null,"size":35300523},{"id":"b438c859-77fc-4f19-be00-6c9bba372a90","file":"DSC_9047.jpg","width":"3822","height":"5809","date":"2023:09:30 17:51:08","thumbnail":null,"size":33896812},{"id":"d42756c0-8637-4507-8eee-ab85203f3baf","file":"DSC_9046.jpg","width":"5809","height":"3822","date":"2023:09:30 17:50:44","thumbnail":null,"size":26639368},{"id":"49a1b179-f726-40d7-b256-45ff89e90837","file":"DSC_9045.jpg","width":"5809","height":"3822","date":"2023:09:30 17:50:43","thumbnail":null,"size":26677835},{"id":"a1246f40-f809-414e-9abb-8d5b3302b472","file":"DSC_9044.jpg","width":"3822","height":"5809","date":"2023:09:30 17:50:34","thumbnail":null,"size":29474160},{"id":"734849ba-e54e-4cb6-8102-27f64edf4283","file":"DSC_9043.jpg","width":"3822","height":"5809","date":"2023:09:30 17:50:32","thumbnail":null,"size":28834333},{"id":"4ca5e9f4-a0df-4957-9f5a-6d8fe7e4a1f5","file":"DSC_9042.jpg","width":"3822","height":"5809","date":"2023:09:30 17:50:28","thumbnail":null,"size":29077392},{"id":"1f6bfe00-7b1b-4d5a-b27b-31abf695a873","file":"DSC_9041.jpg","width":"3822","height":"5809","date":"2023:09:30 17:50:19","thumbnail":null,"size":24515805},{"id":"0c69da75-5341-42a4-9386-557ecc9ba523","file":"DSC_9040.jpg","width":"3822","height":"5809","date":"2023:09:30 17:50:08","thumbnail":null,"size":29527702},{"id":"1d5dbea7-14df-4e4d-8be3-b26810ca3c62","file":"DSC_9038.jpg","width":"3822","height":"5809","date":"2023:09:30 17:48:25","thumbnail":null,"size":27322299},{"id":"9903583e-7dd2-488e-8117-b13d6c3901a0","file":"DSC_9039.jpg","width":"3822","height":"5809","date":"2023:09:30 17:48:25","thumbnail":null,"size":30392000},{"id":"ae9c30f9-3fed-474b-a550-1ff9edf463ef","file":"DSC_9036.jpg","width":"3822","height":"5809","date":"2023:09:30 17:48:24","thumbnail":null,"size":28020628},{"id":"d6845adf-8cb8-4314-bcaa-d32c53488f26","file":"DSC_9037.jpg","width":"3822","height":"5809","date":"2023:09:30 17:48:24","thumbnail":null,"size":27257659},{"id":"f86d6a4d-ab2f-4793-bd16-1ff704106cfb","file":"DSC_9035.jpg","width":"3822","height":"5809","date":"2023:09:30 17:48:22","thumbnail":null,"size":23676285},{"id":"44e2ef9d-f9fd-46d4-82ae-20127ac409a8","file":"DSC_9034.jpg","width":"5809","height":"3822","date":"2023:09:30 17:47:52","thumbnail":null,"size":9948866},{"id":"3099ecd0-187b-4165-8957-24c3ca142a5d","file":"DSC_9033.jpg","width":"5809","height":"3822","date":"2023:09:30 17:47:51","thumbnail":null,"size":10076431},{"id":"ea46d135-c1a7-4c65-8041-c9e50412650f","file":"DSC_9032.jpg","width":"5809","height":"3822","date":"2023:09:30 17:47:50","thumbnail":null,"size":9591211},{"id":"d0d49f41-47c5-41cd-a254-079f1e53bc28","file":"DSC_9030.jpg","width":"5809","height":"3822","date":"2023:09:30 17:47:36","thumbnail":null,"size":7528580},{"id":"c4e436c7-8894-416c-919d-8f71c8254e89","file":"DSC_9031.jpg","width":"5809","height":"3822","date":"2023:09:30 17:47:36","thumbnail":null,"size":7821084},{"id":"abfbf65d-3733-4bd1-a151-7a77c679e13d","file":"DSC_9029.jpg","width":"5809","height":"3822","date":"2023:09:30 17:47:35","thumbnail":null,"size":7478218},{"id":"c1bdf49b-8aac-4192-ab04-379f75662f1a","file":"DSC_9028.jpg","width":"5809","height":"3822","date":"2023:09:30 17:47:31","thumbnail":null,"size":7323915},{"id":"172a7e71-15d0-4e9a-8112-f2dca39bb477","file":"DSC_9027.jpg","width":"5809","height":"3822","date":"2023:09:30 17:47:30","thumbnail":null,"size":7077585},{"id":"f1fdb190-1cbd-45a4-8520-40d317c8adff","file":"DSC_9026.jpg","width":"5809","height":"3822","date":"2023:09:30 17:47:29","thumbnail":null,"size":6883823},{"id":"9b350ecf-4480-4321-bfeb-257e99dbc628","file":"DSC_9024.jpg","width":"5809","height":"3822","date":"2023:09:30 17:46:37","thumbnail":null,"size":15927432},{"id":"d326a9c1-f7b4-4036-b551-c337dba2ddf0","file":"DSC_9023.jpg","width":"5809","height":"3822","date":"2023:09:30 17:46:23","thumbnail":null,"size":15509334},{"id":"11b34288-1d3d-49d8-bfaf-452d88ce8b0b","file":"DSC_9021.jpg","width":"5809","height":"3822","date":"2023:09:30 17:46:08","thumbnail":null,"size":8175515},{"id":"a758bdd6-f8ed-4b32-adbc-b504e0b3b289","file":"DSC_9020.jpg","width":"5809","height":"3822","date":"2023:09:30 17:46:07","thumbnail":null,"size":8580481},{"id":"df17ea74-810d-4a31-9bcb-64e1cde9bc92","file":"DSC_9018.jpg","width":"5809","height":"3822","date":"2023:09:30 17:45:11","thumbnail":null,"size":25900537},{"id":"dd3934cf-3ba2-4701-9297-638b55170971","file":"DSC_9017.jpg","width":"5809","height":"3822","date":"2023:09:30 17:45:09","thumbnail":null,"size":23968127},{"id":"1a6399f0-4745-49bd-bad6-783c6b62529a","file":"DSC_9016.jpg","width":"3822","height":"5809","date":"2023:09:30 17:44:49","thumbnail":null,"size":31015745},{"id":"c2f9d777-0e1c-4043-a77d-b4a946e51369","file":"DSC_9015.jpg","width":"3822","height":"5809","date":"2023:09:30 17:44:48","thumbnail":null,"size":33864069},{"id":"6a7537a2-17d7-4731-92cd-a37d27008fe0","file":"DSC_9013.jpg","width":"3822","height":"5809","date":"2023:09:30 17:42:00","thumbnail":null,"size":28822325},{"id":"fae91554-eb9f-46c0-8ddc-cc2a29e4f9e9","file":"DSC_9011.jpg","width":"3822","height":"5809","date":"2023:09:30 17:41:59","thumbnail":null,"size":28635109},{"id":"4b17f165-d3c9-44df-8444-44fefd682478","file":"DSC_9012.jpg","width":"3822","height":"5809","date":"2023:09:30 17:41:59","thumbnail":null,"size":19392496},{"id":"35ea2ded-a784-4479-bf4a-ec32b1f39528","file":"DSC_9010.jpg","width":"3822","height":"5809","date":"2023:09:30 17:41:57","thumbnail":null,"size":29187645},{"id":"7f9d9f89-2d92-466d-9ea7-138bffe2456b","file":"DSC_9009.jpg","width":"3822","height":"5809","date":"2023:09:30 17:41:13","thumbnail":null,"size":7635968},{"id":"09e92bae-c536-47ba-bf5a-e30f67b95fb9","file":"DSC_9008.jpg","width":"3822","height":"5809","date":"2023:09:30 17:39:16","thumbnail":null,"size":14683865},{"id":"6c015127-8e7d-4112-887e-e407ab238aa4","file":"DSC_9007.jpg","width":"3822","height":"5809","date":"2023:09:30 17:39:14","thumbnail":null,"size":15255462},{"id":"18b25ca1-8dfd-424d-bdfd-e4c749829310","file":"DSC_9005.jpg","width":"3822","height":"5809","date":"2023:09:30 17:38:44","thumbnail":null,"size":28710323},{"id":"50d9734b-b5fe-4867-805b-ed80b5d10c99","file":"DSC_9006.jpg","width":"3822","height":"5809","date":"2023:09:30 17:38:44","thumbnail":null,"size":27612129},{"id":"0d163820-ad10-49e1-be15-0e6b6ddd1df2","file":"DSC_9004.jpg","width":"3822","height":"5809","date":"2023:09:30 17:38:43","thumbnail":null,"size":9597545},{"id":"0d987549-d417-4218-a110-08f97a3c33f4","file":"DSC_9003.jpg","width":"3822","height":"5809","date":"2023:09:30 17:38:24","thumbnail":null,"size":22162954},{"id":"14b6685e-bec3-43f1-a3b8-9dc6c6aa8b7f","file":"DSC_9002.jpg","width":"3822","height":"5809","date":"2023:09:30 17:38:18","thumbnail":null,"size":27428063},{"id":"df15ac64-7d9b-409c-8e00-7200714ad2d4","file":"DSC_9001.jpg","width":"3822","height":"5809","date":"2023:09:30 17:35:31","thumbnail":null,"size":19005208},{"id":"86996e66-1f8d-4ebd-94a3-184f24f4f1b0","file":"DSC_9000.jpg","width":"3822","height":"5809","date":"2023:09:30 17:35:28","thumbnail":null,"size":16524173},{"id":"3640bdd5-1d35-4870-b337-f36e40974bcb","file":"DSC_8999.jpg","width":"5809","height":"3822","date":"2023:09:30 17:35:15","thumbnail":null,"size":22456693},{"id":"47b1d236-f884-4f16-9cb1-a5c365dcdc74","file":"DSC_8998.jpg","width":"5809","height":"3822","date":"2023:09:30 17:35:05","thumbnail":null,"size":18497204},{"id":"abcfe377-9155-4ae6-ad61-022e924e98e7","file":"DSC_8997.jpg","width":"5809","height":"3822","date":"2023:09:30 17:35:03","thumbnail":null,"size":20682715},{"id":"5afadbd0-6e89-45b1-8814-858c4a9cae62","file":"DSC_8996.jpg","width":"3822","height":"5809","date":"2023:09:30 17:34:58","thumbnail":null,"size":13091410},{"id":"e6fd9855-f741-4d2f-9abb-b172efa42a7c","file":"DSC_8993.jpg","width":"3822","height":"5809","date":"2023:09:30 17:34:04","thumbnail":null,"size":27696480},{"id":"c5cd3a8b-f4f7-453b-a588-f6c293eba115","file":"DSC_8994.jpg","width":"3822","height":"5809","date":"2023:09:30 17:34:04","thumbnail":null,"size":27363050},{"id":"63c4e3aa-b72d-40da-b13d-cb4543418068","file":"DSC_8995.jpg","width":"3822","height":"5809","date":"2023:09:30 17:34:04","thumbnail":null,"size":27436245},{"id":"9b47f7d3-225c-47aa-a50a-c05e3943fa8c","file":"DSC_8992.jpg","width":"3822","height":"5809","date":"2023:09:30 17:34:03","thumbnail":null,"size":27809912},{"id":"6b362168-4106-4503-9dfc-4c89870b407a","file":"DSC_8991.jpg","width":"3822","height":"5809","date":"2023:09:30 17:33:06","thumbnail":null,"size":25172106},{"id":"0be0aa9c-8a1d-402f-9780-4a9e51e3fa9e","file":"DSC_8989.jpg","width":"3822","height":"5809","date":"2023:09:30 17:30:06","thumbnail":null,"size":7438876},{"id":"ec90baf5-9038-4d23-9fbd-89c48967e255","file":"DSC_8990.jpg","width":"3822","height":"5809","date":"2023:09:30 17:30:06","thumbnail":null,"size":7455058},{"id":"065f7385-f4b2-4e9e-9766-1e2c9bb945b8","file":"DSC_8988.jpg","width":"3822","height":"5809","date":"2023:09:30 17:30:05","thumbnail":null,"size":7284152},{"id":"064547e9-eec4-490f-9b00-14b849773317","file":"DSC_8987.jpg","width":"3822","height":"5809","date":"2023:09:30 17:30:04","thumbnail":null,"size":7307166},{"id":"6aaef5f9-59a4-496c-b848-ac812b4b3a06","file":"DSC_8986.jpg","width":"3822","height":"5809","date":"2023:09:30 17:30:03","thumbnail":null,"size":7305181},{"id":"f2d159f0-448a-4c00-8912-a81bd6dd6995","file":"DSC_8985.jpg","width":"3822","height":"5809","date":"2023:09:30 17:29:51","thumbnail":null,"size":7101902},{"id":"43ca4d36-7a4a-41f1-8740-7f9250df7fde","file":"DSC_8984.jpg","width":"3822","height":"5809","date":"2023:09:30 17:29:48","thumbnail":null,"size":7535407},{"id":"c67fbdad-b970-4306-96f4-fafa1775e802","file":"DSC_8983.jpg","width":"3822","height":"5809","date":"2023:09:30 17:29:42","thumbnail":null,"size":6693520},{"id":"fe867a86-185b-4f62-b21e-ddca5af5f489","file":"DSC_8982.jpg","width":"3822","height":"5809","date":"2023:09:30 17:27:58","thumbnail":null,"size":29216174},{"id":"74b59ebb-2dc2-4b83-9f68-a32771f149dd","file":"DSC_8981.jpg","width":"3822","height":"5809","date":"2023:09:30 17:27:57","thumbnail":null,"size":23667558},{"id":"e03f4aba-504e-4b9c-b9ce-75519abd9b33","file":"DSC_8980.jpg","width":"3822","height":"5809","date":"2023:09:30 17:27:45","thumbnail":null,"size":25699772},{"id":"66329914-0443-4c5e-bf52-90d69f9e2d3a","file":"DSC_8979.jpg","width":"3822","height":"5809","date":"2023:09:30 17:27:44","thumbnail":null,"size":26323219},{"id":"14bf58fc-4f95-415f-b1d3-3bf35d5c0356","file":"DSC_8977.jpg","width":"3822","height":"5809","date":"2023:09:30 17:27:16","thumbnail":null,"size":8608156},{"id":"52e40d97-8c3d-4b35-b106-060c5658186e","file":"DSC_8978.jpg","width":"3822","height":"5809","date":"2023:09:30 17:27:16","thumbnail":null,"size":8433686},{"id":"a70006f9-3eae-42b7-8193-9f825f368c4e","file":"DSC_8976.jpg","width":"3822","height":"5809","date":"2023:09:30 17:27:14","thumbnail":null,"size":8092453},{"id":"20e6f8cc-e1df-4b6b-b595-cf85960286fb","file":"DSC_8974.jpg","width":"3822","height":"5809","date":"2023:09:30 17:24:09","thumbnail":null,"size":18698421},{"id":"a1f66578-ffbe-4010-8cb3-7de6d8348d06","file":"DSC_8975.jpg","width":"3822","height":"5809","date":"2023:09:30 17:24:09","thumbnail":null,"size":22239790},{"id":"856ee03e-1e03-4eed-9fed-91ee87453b81","file":"DSC_8973.jpg","width":"3822","height":"5809","date":"2023:09:30 17:24:08","thumbnail":null,"size":22128887},{"id":"2e6e37fe-f726-4a6e-abb1-0d8ac391745c","file":"DSC_8972.jpg","width":"3822","height":"5809","date":"2023:09:30 17:23:56","thumbnail":null,"size":9791424},{"id":"30168474-5f08-4819-8d67-47b60d9d48b0","file":"DSC_8971.jpg","width":"3822","height":"5809","date":"2023:09:30 17:23:51","thumbnail":null,"size":8132984},{"id":"976284ce-168c-4a01-bf64-d220763675b0","file":"DSC_8970.jpg","width":"3822","height":"5809","date":"2023:09:30 17:23:50","thumbnail":null,"size":8173566},{"id":"f15fdba8-6731-4e47-8716-1bec34b4a19d","file":"DSC_8969.jpg","width":"3822","height":"5809","date":"2023:09:30 17:23:46","thumbnail":null,"size":9028495},{"id":"d00b26cf-5a2b-415c-8ab2-cbb38bc25173","file":"DSC_8968.jpg","width":"3822","height":"5809","date":"2023:09:30 17:23:44","thumbnail":null,"size":8748979},{"id":"a8488b95-d84b-4f13-8284-70361bc20fba","file":"DSC_8967.jpg","width":"3822","height":"5809","date":"2023:09:30 17:23:43","thumbnail":null,"size":8937246},{"id":"d43d1cea-1a62-4863-aa5f-26102aadeb4b","file":"DSC_8966.jpg","width":"3822","height":"5809","date":"2023:09:30 17:23:36","thumbnail":null,"size":9094728},{"id":"1494508e-5306-4614-8ffc-2522716554d1","file":"DSC_8965.jpg","width":"3822","height":"5809","date":"2023:09:30 17:23:34","thumbnail":null,"size":8769589},{"id":"a3cc55b1-d151-49b4-919f-cf9dfbf8b56a","file":"DSC_8964.jpg","width":"3822","height":"5809","date":"2023:09:30 17:23:32","thumbnail":null,"size":8403532},{"id":"8ab0bea0-b3ec-462a-a480-eca502bfd7ac","file":"DSC_8963.jpg","width":"3822","height":"5809","date":"2023:09:30 17:23:31","thumbnail":null,"size":8228557},{"id":"e887fb29-ebbc-4507-90c6-f74883b2ee0b","file":"DSC_8961.jpg","width":"3822","height":"5809","date":"2023:09:30 17:22:56","thumbnail":null,"size":16840702},{"id":"c1cdaec5-cdf8-4cea-800e-c096148486c0","file":"DSC_8962.jpg","width":"3822","height":"5809","date":"2023:09:30 17:22:56","thumbnail":null,"size":17906626},{"id":"d753fb9d-6975-4553-a493-ba765b1caa7a","file":"DSC_8960.jpg","width":"3822","height":"5809","date":"2023:09:30 17:22:55","thumbnail":null,"size":18268138},{"id":"bea7d1d7-84a2-4e57-940f-12890edc7a36","file":"DSC_8959.jpg","width":"3822","height":"5809","date":"2023:09:30 17:22:23","thumbnail":null,"size":9254229},{"id":"ed77bdef-9e87-48f7-b5eb-ebe98561b1d1","file":"DSC_8958.jpg","width":"3822","height":"5809","date":"2023:09:30 17:22:22","thumbnail":null,"size":9265192},{"id":"bdf494ee-9932-4bcf-8f20-4d7d2d55df7c","file":"DSC_8956.jpg","width":"3822","height":"5809","date":"2023:09:30 17:22:13","thumbnail":null,"size":9491096},{"id":"d03d2296-f7ff-4ab3-b3cc-5f10580d486a","file":"DSC_8957.jpg","width":"3822","height":"5809","date":"2023:09:30 17:22:13","thumbnail":null,"size":8931855},{"id":"0f8aab31-2492-4758-a609-1f16618aad2c","file":"DSC_8955.jpg","width":"3822","height":"5809","date":"2023:09:30 17:22:11","thumbnail":null,"size":9053696},{"id":"95c79b69-3f44-40df-b5a7-bf871a2f2f48","file":"DSC_8952.jpg","width":"3822","height":"5809","date":"2023:09:30 17:21:38","thumbnail":null,"size":15500319},{"id":"c9a0b0d1-5712-426e-b09a-8f63b294d914","file":"DSC_8953.jpg","width":"3822","height":"5809","date":"2023:09:30 17:21:38","thumbnail":null,"size":14582465},{"id":"4c618f99-211b-442b-9bf8-c7ee88fd10d2","file":"DSC_8954.jpg","width":"3822","height":"5809","date":"2023:09:30 17:21:38","thumbnail":null,"size":14466904},{"id":"adfade83-6af2-4cca-893d-fef1794acfe3","file":"DSC_8951.jpg","width":"3822","height":"5809","date":"2023:09:30 17:21:32","thumbnail":null,"size":15596419},{"id":"c9e7071d-663c-4063-a4f9-4a4d85954c69","file":"DSC_8950.jpg","width":"3822","height":"5809","date":"2023:09:30 17:21:31","thumbnail":null,"size":15869443},{"id":"a0dd0cc0-ab4c-4278-99f4-99059f2f8aad","file":"DSC_8949.jpg","width":"5809","height":"3822","date":"2023:09:30 17:20:29","thumbnail":null,"size":19631271},{"id":"00b00578-12b4-4129-acea-a0c119533239","file":"DSC_8948.jpg","width":"3822","height":"5809","date":"2023:09:30 17:18:50","thumbnail":null,"size":25333005},{"id":"b1ed9928-5f12-421e-bd56-a06926897cd6","file":"DSC_8947.jpg","width":"3822","height":"5809","date":"2023:09:30 17:18:48","thumbnail":null,"size":26015829},{"id":"d4993d11-71b3-4a8d-af2e-a10898bdef4e","file":"DSC_8946.jpg","width":"5809","height":"3822","date":"2023:09:30 17:18:10","thumbnail":null,"size":11867831},{"id":"17bb1968-7a94-4729-930e-a367919951b5","file":"DSC_8945.jpg","width":"3822","height":"5809","date":"2023:09:30 17:16:57","thumbnail":null,"size":9087381},{"id":"f093b451-309f-4552-8e05-121768978f29","file":"DSC_8944.jpg","width":"3822","height":"5809","date":"2023:09:30 17:16:42","thumbnail":null,"size":10555950},{"id":"f95a7829-5f9c-4035-bc10-1730a7cd196f","file":"DSC_8943.jpg","width":"3822","height":"5809","date":"2023:09:30 17:15:56","thumbnail":null,"size":8066762},{"id":"932b2f55-740d-4938-be8b-6da56801eb53","file":"DSC_8942.jpg","width":"3822","height":"5809","date":"2023:09:30 17:15:53","thumbnail":null,"size":7974849},{"id":"b80e8846-aaa4-4a2d-8542-6608481c3d7d","file":"DSC_8941.jpg","width":"5809","height":"3822","date":"2023:09:30 17:15:19","thumbnail":null,"size":10800403},{"id":"5cb28b80-0955-4eef-b327-2e7cd8019f40","file":"DSC_8940.jpg","width":"5809","height":"3822","date":"2023:09:30 17:15:17","thumbnail":null,"size":11284498},{"id":"bb8388f9-cfd0-488a-b0a7-03af9a1f6d8c","file":"DSC_8939.jpg","width":"5809","height":"3822","date":"2023:09:30 17:15:14","thumbnail":null,"size":10654452},{"id":"6a02f360-73ef-4f7f-9e75-73858638fd70","file":"DSC_8938.jpg","width":"5809","height":"3822","date":"2023:09:30 17:14:53","thumbnail":null,"size":10329362},{"id":"e717b900-de23-4f76-916e-67d3abdaf08c","file":"DSC_8937.jpg","width":"3822","height":"5809","date":"2023:09:30 17:14:48","thumbnail":null,"size":9254246},{"id":"07fac45b-f4d8-420e-84c7-a19d21258177","file":"DSC_8936.jpg","width":"3822","height":"5809","date":"2023:09:30 17:14:46","thumbnail":null,"size":8822862},{"id":"697ca39f-b237-4142-aa6b-150774a77e3a","file":"DSC_8935.jpg","width":"5809","height":"3822","date":"2023:09:30 17:14:17","thumbnail":null,"size":12385264},{"id":"5adab404-5430-4a2f-8631-2af4e80fe462","file":"DSC_8934.jpg","width":"3822","height":"5809","date":"2023:09:30 17:13:55","thumbnail":null,"size":7584872},{"id":"c15ab834-bc4c-44ac-853c-974428184265","file":"DSC_8933.jpg","width":"3822","height":"5809","date":"2023:09:30 17:13:54","thumbnail":null,"size":7935996},{"id":"156f77b3-f2ff-4bdc-8dc2-d44493816b6a","file":"DSC_8932.jpg","width":"3822","height":"5809","date":"2023:09:30 17:13:44","thumbnail":null,"size":15546913},{"id":"d12e2cb7-86f4-4484-b392-7f1300005d4a","file":"DSC_8931.jpg","width":"3822","height":"5809","date":"2023:09:30 17:13:43","thumbnail":null,"size":15035908},{"id":"a841e490-4fd3-4ac3-9ea8-3e7e4fbaf843","file":"DSC_8930.jpg","width":"5809","height":"3822","date":"2023:09:30 17:13:09","thumbnail":null,"size":18525333},{"id":"4e54bb62-7b3e-4695-bddf-027ae0dff5c6","file":"DSC_8929.jpg","width":"5809","height":"3822","date":"2023:09:30 17:12:27","thumbnail":null,"size":10125177},{"id":"d41dd7ad-7eb2-45f4-9427-efb542b422e1","file":"DSC_8928.jpg","width":"5809","height":"3822","date":"2023:09:30 17:11:51","thumbnail":null,"size":10755913},{"id":"ea5afef0-21c4-4c6f-9a5e-e0f6a2ff9330","file":"DSC_8927.jpg","width":"5809","height":"3822","date":"2023:09:30 17:11:23","thumbnail":null,"size":14606704},{"id":"a1ddb38e-2d13-4db0-9899-be64bb62f90b","file":"DSC_8926.jpg","width":"5809","height":"3822","date":"2023:09:30 17:11:02","thumbnail":null,"size":11439088},{"id":"4b92c6b1-d1b6-4ac9-b0ec-99c87f4e9a66","file":"DSC_8925.jpg","width":"3822","height":"5809","date":"2023:09:30 17:10:27","thumbnail":null,"size":18071905},{"id":"cb5c1c7d-7810-479d-82a7-909c3696916b","file":"DSC_8924.jpg","width":"5809","height":"3822","date":"2023:09:30 17:10:02","thumbnail":null,"size":14254710},{"id":"0696dca3-779b-463b-90cd-0915dc558d2d","file":"DSC_8923.jpg","width":"5809","height":"3822","date":"2023:09:30 17:09:51","thumbnail":null,"size":13578712},{"id":"428a2dfc-190e-4f96-8c69-2e569b655558","file":"DSC_8922.jpg","width":"3822","height":"5809","date":"2023:09:30 17:09:21","thumbnail":null,"size":16345943},{"id":"fbbe8166-3138-4957-9397-09ac01ae0f93","file":"DSC_8921.jpg","width":"5809","height":"3822","date":"2023:09:30 17:09:08","thumbnail":null,"size":21196128},{"id":"4fdbc772-55dc-4742-9132-dcca8ebeeb2d","file":"DSC_8920.jpg","width":"3822","height":"5809","date":"2023:09:30 17:08:06","thumbnail":null,"size":24940408},{"id":"74c5460f-d77f-459a-ab7b-ad2bac797150","file":"DSC_8919.jpg","width":"3822","height":"5809","date":"2023:09:30 17:07:56","thumbnail":null,"size":23302402},{"id":"b4c0671c-35f7-426b-bf63-0f5db9a33e8e","file":"DSC_8918.jpg","width":"3822","height":"5809","date":"2023:09:30 17:06:07","thumbnail":null,"size":22809504},{"id":"c6a61213-0639-4bc9-849a-d2f3ac253492","file":"DSC_8917.jpg","width":"3822","height":"5809","date":"2023:09:30 17:04:51","thumbnail":null,"size":14656588},{"id":"16383b55-a6f2-422b-929d-054f9dbd23b9","file":"DSC_8916.jpg","width":"3822","height":"5809","date":"2023:09:30 17:04:38","thumbnail":null,"size":21366106},{"id":"560070eb-86b2-4637-8d1f-13213753cd27","file":"DSC_8915.jpg","width":"3822","height":"5809","date":"2023:09:30 17:04:18","thumbnail":null,"size":17434808},{"id":"03487610-8e09-4cf2-9625-829db8036cbe","file":"DSC_8914.jpg","width":"3822","height":"5809","date":"2023:09:30 17:04:05","thumbnail":null,"size":21309359},{"id":"d4f9e69b-f2d7-4744-9c77-118b07fe7eeb","file":"DSC_8913.jpg","width":"3822","height":"5809","date":"2023:09:30 17:03:59","thumbnail":null,"size":21035449},{"id":"99c7ff28-bdb6-4ecb-a1c4-a89d3087f5f9","file":"DSC_8912.jpg","width":"3822","height":"5809","date":"2023:09:30 17:03:14","thumbnail":null,"size":20910413},{"id":"38392bc2-e167-4ea0-b01e-d071a6e055e6","file":"DSC_8911.jpg","width":"3822","height":"5809","date":"2023:09:30 17:03:09","thumbnail":null,"size":19729159},{"id":"adb6ca6a-1f92-43c6-9c01-b82c5651fb01","file":"DSC_8910.jpg","width":"3822","height":"5809","date":"2023:09:30 17:03:07","thumbnail":null,"size":15462604},{"id":"7eaf3eca-0bd6-47e9-93d4-098689bd11b3","file":"DSC_8909.jpg","width":"3822","height":"5809","date":"2023:09:30 17:03:06","thumbnail":null,"size":17184629},{"id":"e0110df9-2450-41b5-83e1-f34485328eb4","file":"DSC_8908.jpg","width":"3822","height":"5809","date":"2023:09:30 17:03:03","thumbnail":null,"size":16407438},{"id":"f0e3223e-74b5-4888-9ff7-e0ce9d73c9be","file":"DSC_8907.jpg","width":"3822","height":"5809","date":"2023:09:30 17:02:57","thumbnail":null,"size":8214104},{"id":"e5759511-c77b-425e-a858-265189726d4a","file":"DSC_8906.jpg","width":"3822","height":"5809","date":"2023:09:30 17:02:50","thumbnail":null,"size":8689366},{"id":"2998f02c-85e5-42bb-8fcd-bf43b160217a","file":"DSC_8905.jpg","width":"5809","height":"3822","date":"2023:09:30 17:02:38","thumbnail":null,"size":10601024},{"id":"6327cacb-b47b-434a-b8d6-9dbe5eed978d","file":"DSC_8904.jpg","width":"5809","height":"3822","date":"2023:09:30 17:02:36","thumbnail":null,"size":10355874},{"id":"cb63d3f9-1171-415e-b289-c9a2ab30f46b","file":"DSC_8903.jpg","width":"5809","height":"3822","date":"2023:09:30 17:02:33","thumbnail":null,"size":10126318},{"id":"b197b80a-6de9-47f7-88d2-0cdc52ca261e","file":"DSC_8901.jpg","width":"5809","height":"3822","date":"2023:09:30 17:02:03","thumbnail":null,"size":14804093},{"id":"063db201-5dc9-4aaf-af7b-05a6201acb6a","file":"DSC_8900.jpg","width":"3822","height":"5809","date":"2023:09:30 17:01:40","thumbnail":null,"size":27536661},{"id":"ea1a878a-29d2-4fdf-9d72-ebb7eb6dd129","file":"DSC_8899.jpg","width":"3822","height":"5809","date":"2023:09:30 17:01:38","thumbnail":null,"size":27328278},{"id":"48658364-a881-45ec-9671-d9b5055b00a7","file":"DSC_8898.jpg","width":"3822","height":"5809","date":"2023:09:30 17:01:30","thumbnail":null,"size":26293136},{"id":"d8ebbd1c-9c98-4226-9582-427066f69cee","file":"DSC_8897.jpg","width":"3822","height":"5809","date":"2023:09:30 17:01:13","thumbnail":null,"size":25251674},{"id":"b99ccb0a-49d1-4f2a-a12e-6ffe973aeb98","file":"DSC_8896.jpg","width":"3822","height":"5809","date":"2023:09:30 17:00:42","thumbnail":null,"size":7255034},{"id":"206b995d-e086-4a59-b0c6-9649d26dfbd5","file":"DSC_8895.jpg","width":"3822","height":"5809","date":"2023:09:30 17:00:40","thumbnail":null,"size":7268399},{"id":"bdcc2161-c961-469c-ac47-abcc4f7d74a9","file":"DSC_8893.jpg","width":"3822","height":"5809","date":"2023:09:30 17:00:14","thumbnail":null,"size":7358564},{"id":"835fa6be-21da-4bbc-a88f-f746b42c689e","file":"DSC_8894.jpg","width":"3822","height":"5809","date":"2023:09:30 17:00:14","thumbnail":null,"size":7194052},{"id":"ba8cc621-c0f4-4e4f-8a2c-7e65f1ba5157","file":"DSC_8892.jpg","width":"3822","height":"5809","date":"2023:09:30 17:00:12","thumbnail":null,"size":7211245},{"id":"02a3bcf9-05fc-4071-aa6f-aa4491419f8f","file":"DSC_8891.jpg","width":"3822","height":"5809","date":"2023:09:30 17:00:11","thumbnail":null,"size":7570110},{"id":"ebaa8dbc-a840-4db3-a8d1-e38b3381058c","file":"DSC_8890.jpg","width":"5809","height":"3822","date":"2023:09:30 16:59:49","thumbnail":null,"size":11883692},{"id":"b04e0913-7293-4932-aea6-bfd1b9f1ff43","file":"DSC_8889.jpg","width":"5809","height":"3822","date":"2023:09:30 16:59:48","thumbnail":null,"size":11073758},{"id":"4463a5c6-3ca0-4205-a7c2-ec5dac95dfa8","file":"DSC_8888.jpg","width":"5809","height":"3822","date":"2023:09:30 16:59:47","thumbnail":null,"size":10732735},{"id":"ed3e2148-e8d9-46ec-8656-7e88a8aebe4a","file":"DSC_8887.jpg","width":"3822","height":"5809","date":"2023:09:30 16:59:26","thumbnail":null,"size":22387169},{"id":"638153ae-e33f-4984-a918-1f0c302dee1b","file":"DSC_8885.jpg","width":"3822","height":"5809","date":"2023:09:30 16:58:13","thumbnail":null,"size":18626878},{"id":"a65b9433-a201-4e51-bb2e-c73d53413636","file":"DSC_8886.jpg","width":"3822","height":"5809","date":"2023:09:30 16:58:13","thumbnail":null,"size":18746701},{"id":"97caee6d-f690-4445-a5c6-75721deb1abb","file":"DSC_8883.jpg","width":"3822","height":"5809","date":"2023:09:30 16:58:12","thumbnail":null,"size":18374388},{"id":"2f078de6-ff28-4ca9-bf73-499487244d7a","file":"DSC_8884.jpg","width":"3822","height":"5809","date":"2023:09:30 16:58:12","thumbnail":null,"size":18642892},{"id":"77553a9d-b4c8-4a7a-92f1-9b223d8f0a5a","file":"DSC_8882.jpg","width":"3822","height":"5809","date":"2023:09:30 16:58:11","thumbnail":null,"size":16585301},{"id":"999775d9-b2f4-40a4-aded-0da0bd0f2cca","file":"DSC_8880.jpg","width":"3822","height":"5809","date":"2023:09:30 16:57:51","thumbnail":null,"size":26332299},{"id":"6ba0f794-435c-408a-8ecd-74064a2e8112","file":"DSC_8881.jpg","width":"3822","height":"5809","date":"2023:09:30 16:57:51","thumbnail":null,"size":26153320},{"id":"8d5651d8-357d-499e-be04-907c6efb8b1d","file":"DSC_8879.jpg","width":"3822","height":"5809","date":"2023:09:30 16:57:50","thumbnail":null,"size":27373957},{"id":"af9edc16-f593-4637-bf71-1cb416d32e35","file":"DSC_8878.jpg","width":"3822","height":"5809","date":"2023:09:30 16:57:46","thumbnail":null,"size":20695332},{"id":"00c326a6-5ec5-4bd5-8a48-42ea89473712","file":"DSC_8877.jpg","width":"3822","height":"5809","date":"2023:09:30 16:57:43","thumbnail":null,"size":22788799},{"id":"8ffe691d-3cb6-49ac-a71b-8327508cbb2a","file":"DSC_8876.jpg","width":"3822","height":"5809","date":"2023:09:30 16:57:38","thumbnail":null,"size":25015326},{"id":"aeb5199d-10a6-4acf-a691-b1d341a09e74","file":"DSC_8875.jpg","width":"3822","height":"5809","date":"2023:09:30 16:57:28","thumbnail":null,"size":8573781},{"id":"43e66425-0399-481d-b655-ef36cc93c9dc","file":"DSC_8874.jpg","width":"3822","height":"5809","date":"2023:09:30 16:57:23","thumbnail":null,"size":15290534},{"id":"4f43cf81-956e-41bc-8cdc-64b3684821d0","file":"DSC_8872.jpg","width":"3822","height":"5809","date":"2023:09:30 16:57:19","thumbnail":null,"size":15810326},{"id":"903cbdbe-8b19-4c89-9407-e061285a76a2","file":"DSC_8873.jpg","width":"3822","height":"5809","date":"2023:09:30 16:57:19","thumbnail":null,"size":13563968},{"id":"132a4193-2851-42ba-87cb-266022e3fab4","file":"DSC_8870.jpg","width":"3822","height":"5809","date":"2023:09:30 16:57:05","thumbnail":null,"size":16577121},{"id":"c0568640-f36f-4598-a44f-5f810bd6c65a","file":"DSC_8871.jpg","width":"3822","height":"5809","date":"2023:09:30 16:57:05","thumbnail":null,"size":16332926},{"id":"79c480da-fa87-4e06-b509-a243c124018e","file":"DSC_8869.jpg","width":"3822","height":"5809","date":"2023:09:30 16:57:03","thumbnail":null,"size":15383333},{"id":"e2f59b13-40df-4beb-9209-c0f2277232cf","file":"DSC_8868.jpg","width":"3822","height":"5809","date":"2023:09:30 16:56:54","thumbnail":null,"size":12193173},{"id":"cfb80ca3-2082-46f1-bfd1-a327fde5d740","file":"DSC_8867.jpg","width":"3822","height":"5809","date":"2023:09:30 16:56:49","thumbnail":null,"size":11999115},{"id":"6b2050e8-d84e-4caf-9f09-0643fbde4411","file":"DSC_8866.jpg","width":"3822","height":"5809","date":"2023:09:30 16:56:48","thumbnail":null,"size":11004923},{"id":"448d88b7-ca68-47be-a2a7-22a468e7bf22","file":"DSC_8865.jpg","width":"3822","height":"5809","date":"2023:09:30 16:56:31","thumbnail":null,"size":6878856},{"id":"40e9b81a-d29d-4412-87a3-d694606c1624","file":"DSC_8864.jpg","width":"3822","height":"5809","date":"2023:09:30 16:56:30","thumbnail":null,"size":6973713},{"id":"6d1337f6-684a-44b3-a065-8125e24c6616","file":"DSC_8863.jpg","width":"3822","height":"5809","date":"2023:09:30 16:56:29","thumbnail":null,"size":6485946},{"id":"eb10078a-0527-44c3-ac40-6d1f1a2532a7","file":"DSC_8862.jpg","width":"3822","height":"5809","date":"2023:09:30 16:56:23","thumbnail":null,"size":7360818},{"id":"9d3a97e4-5ee1-4da4-b901-0c8cda389444","file":"DSC_8860.jpg","width":"3822","height":"5809","date":"2023:09:30 16:55:51","thumbnail":null,"size":9750344},{"id":"f8f93712-3fc4-4dd4-b306-cf463d6e8d33","file":"DSC_8859.jpg","width":"3822","height":"5809","date":"2023:09:30 16:55:50","thumbnail":null,"size":12274561},{"id":"e0e27d9e-f30e-4fae-b9f8-a9fec46c942d","file":"DSC_8858.jpg","width":"3822","height":"5809","date":"2023:09:30 16:55:46","thumbnail":null,"size":9951249},{"id":"56fbda47-6500-4037-b198-b464cc41a3e6","file":"DSC_8857.jpg","width":"5809","height":"3822","date":"2023:09:30 16:55:37","thumbnail":null,"size":5688294},{"id":"4768b2c4-7cce-4b1b-abb9-86da63fbceab","file":"DSC_8856.jpg","width":"5809","height":"3822","date":"2023:09:30 16:55:35","thumbnail":null,"size":5868752}],"image_count":345,"video_count":0,"heic_count":1,"youtube_count":0}},"image_count":345,"size":5340161183,"video_count":0,"youtube_count":0,"directory_info":{"directory":"11G","git":"5.2G","thumbnails":"42M","folders":[{"size":"5.0G","name":"images","storage_path":"\/mnt\/TOSHIBA-DATA2\/khieu-ngoan-git\/tanaka-20231020-p2\/images"}]}}