{"days":{"images":{"size":172279187,"files":[{"id":"70ac7ac8-2f7b-4acb-9f41-59ccbe68203f","file":"DSC_9214.jpg","width":"1053","height":"1600","date":"2023:09:30 18:51:59","thumbnail":null,"size":262671},{"id":"19e51010-dfd4-4d05-b252-68c1246f8b1e","file":"DSC_9213.jpg","width":"1053","height":"1600","date":"2023:09:30 18:51:58","thumbnail":null,"size":294738},{"id":"9469493f-599b-47ed-bb75-352b7a5fc26f","file":"DSC_9212.jpg","width":"1053","height":"1600","date":"2023:09:30 18:51:57","thumbnail":null,"size":289997},{"id":"4daf3448-b93d-4f00-a547-0e6c8fae4e77","file":"DSC_9211.jpg","width":"1053","height":"1600","date":"2023:09:30 18:51:55","thumbnail":null,"size":270577},{"id":"6879f9a6-6665-421c-82b9-54dced719a61","file":"DSC_9209.jpg","width":"1053","height":"1600","date":"2023:09:30 18:51:37","thumbnail":null,"size":602955},{"id":"c33ce029-0ca3-4646-9859-684ece23b660","file":"DSC_9210.jpg","width":"1053","height":"1600","date":"2023:09:30 18:51:37","thumbnail":null,"size":606295},{"id":"36ce3c89-bba8-4c9c-98d4-edee412fe387","file":"DSC_9208.jpg","width":"1053","height":"1600","date":"2023:09:30 18:51:36","thumbnail":null,"size":563940},{"id":"537ad558-a63c-4229-8c93-b3491c137ac6","file":"DSC_9207.jpg","width":"1053","height":"1600","date":"2023:09:30 18:51:31","thumbnail":null,"size":568827},{"id":"85e3bcf5-145e-4e5a-8c5c-b3a7225ec3b9","file":"DSC_9206.jpg","width":"1053","height":"1600","date":"2023:09:30 18:51:28","thumbnail":null,"size":645747},{"id":"4129e16e-e79f-4ba5-8ea9-50ef2dd37bb1","file":"DSC_9203.jpg","width":"1053","height":"1600","date":"2023:09:30 18:47:05","thumbnail":null,"size":700439},{"id":"d61425dc-55d7-488e-b6bd-f313560ebfc8","file":"DSC_9204.jpg","width":"1053","height":"1600","date":"2023:09:30 18:47:05","thumbnail":null,"size":690195},{"id":"bd0ba473-3dbe-49f2-b372-3b0d8f77de11","file":"DSC_9201.jpg","width":"1053","height":"1600","date":"2023:09:30 18:47:04","thumbnail":null,"size":661733},{"id":"8641d92f-0df6-443c-b4f2-6c31e09be885","file":"DSC_9202.jpg","width":"1053","height":"1600","date":"2023:09:30 18:47:04","thumbnail":null,"size":694071},{"id":"2904d0c8-45ab-4447-b620-ff362437526d","file":"DSC_9199.jpg","width":"2432","height":"1600","date":"2023:09:30 18:40:29","thumbnail":null,"size":616994},{"id":"6aeed346-d3d8-4b07-8611-4d8ccd3d8c78","file":"DSC_9200.jpg","width":"2432","height":"1600","date":"2023:09:30 18:40:29","thumbnail":null,"size":606697},{"id":"c68f0c85-09cf-49e3-b2a0-83de7881055d","file":"DSC_9198.jpg","width":"2432","height":"1600","date":"2023:09:30 18:40:26","thumbnail":null,"size":651937},{"id":"38d3ce50-5660-42a0-a11d-f0a4243a3805","file":"DSC_9196.jpg","width":"1053","height":"1600","date":"2023:09:30 18:36:35","thumbnail":null,"size":592129},{"id":"a1dbd956-0241-46fe-a0aa-98f2df0381aa","file":"DSC_9197.jpg","width":"1053","height":"1600","date":"2023:09:30 18:36:35","thumbnail":null,"size":593190},{"id":"2215a7e6-49d6-48ea-bb37-d43f1c5dfb4e","file":"DSC_9195.jpg","width":"1053","height":"1600","date":"2023:09:30 18:36:34","thumbnail":null,"size":587275},{"id":"98a2abcb-3fd1-46ae-94b2-fa4c6861498c","file":"DSC_9194.jpg","width":"1053","height":"1600","date":"2023:09:30 18:35:51","thumbnail":null,"size":545135},{"id":"6a748da5-d4e3-4a7f-99a9-e4ff5d4da117","file":"DSC_9193.jpg","width":"1053","height":"1600","date":"2023:09:30 18:35:50","thumbnail":null,"size":542227},{"id":"760a05f5-995f-480d-8822-b87d87d4cbbc","file":"DSC_9192.jpg","width":"1053","height":"1600","date":"2023:09:30 18:35:49","thumbnail":null,"size":620171},{"id":"7b7b0f3f-885b-4e21-9abf-46bceebcb32f","file":"DSC_9190.jpg","width":"1053","height":"1600","date":"2023:09:30 18:34:27","thumbnail":null,"size":540869},{"id":"d7eec05c-9147-4e1e-9e5d-50c525a07906","file":"DSC_9191.jpg","width":"1053","height":"1600","date":"2023:09:30 18:34:27","thumbnail":null,"size":552310},{"id":"4cf8fcdc-9d4b-4eed-82bf-0b8b0b581294","file":"DSC_9189.jpg","width":"1053","height":"1600","date":"2023:09:30 18:34:26","thumbnail":null,"size":345639},{"id":"ed70ce57-4947-42c5-a8b3-a4130e3aa03b","file":"DSC_9188.jpg","width":"1053","height":"1600","date":"2023:09:30 18:34:25","thumbnail":null,"size":618212},{"id":"4dc49c04-9a9a-4bf3-853a-210a826b383c","file":"DSC_9187.jpg","width":"1053","height":"1600","date":"2023:09:30 18:34:24","thumbnail":null,"size":530658},{"id":"a69c42af-6db7-426e-a8cb-2524bdcf2ec5","file":"DSC_9185.jpg","width":"1053","height":"1600","date":"2023:09:30 18:34:23","thumbnail":null,"size":555749},{"id":"7fcabbb5-e071-4e02-9e23-4df5c51a68fd","file":"DSC_9186.jpg","width":"1053","height":"1600","date":"2023:09:30 18:34:23","thumbnail":null,"size":555740},{"id":"1bfb4154-8605-48d8-bc17-fa87db8a54b6","file":"DSC_9183.jpg","width":"1053","height":"1600","date":"2023:09:30 18:34:08","thumbnail":null,"size":547737},{"id":"c5b4d778-bbd9-437d-a3b2-8578a317d167","file":"DSC_9184.jpg","width":"1053","height":"1600","date":"2023:09:30 18:34:08","thumbnail":null,"size":448717},{"id":"7a399999-b410-4870-af21-7492d0b5bbad","file":"DSC_9182.jpg","width":"1053","height":"1600","date":"2023:09:30 18:32:55","thumbnail":null,"size":604976},{"id":"9cf48b6b-b677-4a0d-a405-d2b690281d70","file":"DSC_9181.jpg","width":"1053","height":"1600","date":"2023:09:30 18:32:43","thumbnail":null,"size":501294},{"id":"378f1f61-d6f0-48f9-bf7f-db5e026b6891","file":"DSC_9180.jpg","width":"1053","height":"1600","date":"2023:09:30 18:32:42","thumbnail":null,"size":414521},{"id":"78c469ce-166b-4407-9aff-c7255c2ecbb7","file":"DSC_9179.jpg","width":"1053","height":"1600","date":"2023:09:30 18:32:35","thumbnail":null,"size":543828},{"id":"388bd7e8-9ff8-40c6-ac90-de31942e00b2","file":"DSC_9178.jpg","width":"1053","height":"1600","date":"2023:09:30 18:32:15","thumbnail":null,"size":385104},{"id":"95f2f05a-12a9-4ce1-8a2f-b68e4c03c242","file":"DSC_9177.jpg","width":"1053","height":"1600","date":"2023:09:30 18:32:12","thumbnail":null,"size":389779},{"id":"877b1935-4f32-45d3-b5d6-23549c725118","file":"DSC_9176.jpg","width":"1053","height":"1600","date":"2023:09:30 18:32:11","thumbnail":null,"size":354293},{"id":"5c7c562e-c940-4035-9c82-1dde683eb093","file":"DSC_9175.jpg","width":"2432","height":"1600","date":"2023:09:30 18:32:04","thumbnail":null,"size":454742},{"id":"7cd4a104-7adb-4de1-9ae9-66ddca00dd70","file":"DSC_9174.jpg","width":"2432","height":"1600","date":"2023:09:30 18:32:03","thumbnail":null,"size":511001},{"id":"a222053f-bed7-4fea-b737-c907256e9cb1","file":"DSC_9173.jpg","width":"2432","height":"1600","date":"2023:09:30 18:32:02","thumbnail":null,"size":433008},{"id":"edddfab2-ff80-4a1d-846e-86896156626f","file":"DSC_9172.jpg","width":"1053","height":"1600","date":"2023:09:30 18:31:55","thumbnail":null,"size":361589},{"id":"aa2ae686-2a1a-45b9-8274-d1f0bac8a9b2","file":"DSC_9171.jpg","width":"1053","height":"1600","date":"2023:09:30 18:31:50","thumbnail":null,"size":306965},{"id":"2958d1cd-72a8-404c-bac0-104aac50f74f","file":"DSC_9170.jpg","width":"1053","height":"1600","date":"2023:09:30 18:31:49","thumbnail":null,"size":347915},{"id":"ea591f9a-264e-4b77-909d-938c541a59a3","file":"DSC_9168.jpg","width":"1053","height":"1600","date":"2023:09:30 18:31:21","thumbnail":null,"size":612911},{"id":"7863e9ce-a5a3-4b41-9db0-762d98ec28f1","file":"DSC_9169.jpg","width":"1053","height":"1600","date":"2023:09:30 18:31:21","thumbnail":null,"size":613133},{"id":"2d3e1a87-2d60-47d2-9dac-447eb65e98c5","file":"DSC_9167.jpg","width":"1053","height":"1600","date":"2023:09:30 18:31:20","thumbnail":null,"size":550492},{"id":"ace72be4-97cd-4019-86f5-77dfa4a0b6b9","file":"DSC_9166.jpg","width":"1053","height":"1600","date":"2023:09:30 18:31:18","thumbnail":null,"size":584207},{"id":"b794b486-9d54-4386-89b3-dbd077e32b4d","file":"DSC_9164.jpg","width":"2432","height":"1600","date":"2023:09:30 18:29:03","thumbnail":null,"size":1144912},{"id":"b5a2346b-1047-48e9-be1f-be413e6dba62","file":"DSC_9163.jpg","width":"2432","height":"1600","date":"2023:09:30 18:28:59","thumbnail":null,"size":722622},{"id":"da92484b-edb2-48f9-8865-a8d74bddaae0","file":"DSC_9162.jpg","width":"1053","height":"1600","date":"2023:09:30 18:28:48","thumbnail":null,"size":248087},{"id":"5400f85a-0a43-4a56-8f81-c51e09bfc01c","file":"DSC_9161.jpg","width":"1053","height":"1600","date":"2023:09:30 18:28:45","thumbnail":null,"size":268891},{"id":"01c1f9da-39dd-4f62-aee3-bd0c626e4330","file":"DSC_9160.jpg","width":"2432","height":"1600","date":"2023:09:30 18:28:33","thumbnail":null,"size":436344},{"id":"ef2cef67-5a2e-4ffd-a464-852b7c5da6e5","file":"DSC_9159.jpg","width":"2432","height":"1600","date":"2023:09:30 18:28:32","thumbnail":null,"size":347997},{"id":"3a21435c-77d6-403e-ada3-8f3957a903ae","file":"DSC_9158.jpg","width":"2432","height":"1600","date":"2023:09:30 18:28:31","thumbnail":null,"size":402999},{"id":"2ed38489-dbc3-48fb-8fc5-945225ba3409","file":"DSC_9157.jpg","width":"1053","height":"1600","date":"2023:09:30 18:28:24","thumbnail":null,"size":208822},{"id":"043e55d3-96ad-4ad8-8565-62c0fb58e16b","file":"DSC_9156.jpg","width":"1053","height":"1600","date":"2023:09:30 18:28:23","thumbnail":null,"size":250966},{"id":"2061bc28-9ab5-443c-b6bc-067275b4c062","file":"DSC_9155.jpg","width":"1053","height":"1600","date":"2023:09:30 18:28:19","thumbnail":null,"size":333068},{"id":"1c5dbc98-358a-4c22-9928-df39ea901adb","file":"DSC_9154.jpg","width":"1053","height":"1600","date":"2023:09:30 18:28:18","thumbnail":null,"size":330041},{"id":"f47da6f2-daeb-4459-ac3f-9a0f39fc50d3","file":"DSC_9152.jpg","width":"1053","height":"1600","date":"2023:09:30 18:28:17","thumbnail":null,"size":344726},{"id":"2e0772c2-2003-4eee-93fe-ee9ab582bc76","file":"DSC_9153.jpg","width":"1053","height":"1600","date":"2023:09:30 18:28:17","thumbnail":null,"size":350914},{"id":"e1f2ec9a-51e5-4771-94b0-2700fb7b6469","file":"DSC_9151.jpg","width":"1053","height":"1600","date":"2023:09:30 18:28:14","thumbnail":null,"size":385116},{"id":"11194383-eee9-46a6-b232-c655e5620520","file":"DSC_9150.jpg","width":"1053","height":"1600","date":"2023:09:30 18:28:09","thumbnail":null,"size":434254},{"id":"ed268d67-3e27-4554-8eae-9ae59fd6423e","file":"DSC_9149.jpg","width":"1053","height":"1600","date":"2023:09:30 18:27:54","thumbnail":null,"size":503709},{"id":"35649138-d27d-42ab-b72b-f16af3394148","file":"DSC_9148.jpg","width":"1053","height":"1600","date":"2023:09:30 18:26:22","thumbnail":null,"size":477863},{"id":"ea4043ca-d3d3-4bc9-9cfa-27de7f22582f","file":"DSC_9147.jpg","width":"1053","height":"1600","date":"2023:09:30 18:26:21","thumbnail":null,"size":491938},{"id":"c5953b0e-a80b-49bf-aa46-17bca2d41735","file":"DSC_9146.jpg","width":"1053","height":"1600","date":"2023:09:30 18:26:18","thumbnail":null,"size":506330},{"id":"a403be16-c8d6-47a9-9a9b-8c7cd582c913","file":"DSC_9145.jpg","width":"1053","height":"1600","date":"2023:09:30 18:26:17","thumbnail":null,"size":461453},{"id":"b723af45-bd2e-4242-9619-67adcdcb4b51","file":"DSC_9144.jpg","width":"1053","height":"1600","date":"2023:09:30 18:25:18","thumbnail":null,"size":489722},{"id":"b298fdc8-04c4-43c3-b24d-acbc3fa9afc9","file":"DSC_9143.jpg","width":"1053","height":"1600","date":"2023:09:30 18:25:16","thumbnail":null,"size":480035},{"id":"4d8202f6-5e54-47c1-b47b-052983604ae8","file":"DSC_9141.jpg","width":"2432","height":"1600","date":"2023:09:30 18:13:32","thumbnail":null,"size":364200},{"id":"8e7928b8-dbda-458b-bf7c-68e774005019","file":"DSC_9142.jpg","width":"2432","height":"1600","date":"2023:09:30 18:13:32","thumbnail":null,"size":321360},{"id":"f2b9ed99-db46-42f1-8a87-908a6700afb1","file":"DSC_9140.jpg","width":"2432","height":"1600","date":"2023:09:30 18:13:31","thumbnail":null,"size":424113},{"id":"5d987948-87c1-41fa-88e6-b7aef24694a0","file":"DSC_9139.jpg","width":"2432","height":"1600","date":"2023:09:30 18:13:30","thumbnail":null,"size":420184},{"id":"084a5772-d0b8-4d56-8788-6076b7ea3ba6","file":"DSC_9138.jpg","width":"2432","height":"1600","date":"2023:09:30 18:13:20","thumbnail":null,"size":398003},{"id":"e3085414-ea88-4f7f-b312-b998c2bef048","file":"DSC_9137.jpg","width":"2432","height":"1600","date":"2023:09:30 18:13:00","thumbnail":null,"size":500624},{"id":"6ee47f11-8add-4e6e-b1a5-c4ff733e9b4b","file":"DSC_9136.jpg","width":"2432","height":"1600","date":"2023:09:30 18:12:13","thumbnail":null,"size":304216},{"id":"37520379-c9fd-4369-9e84-e97df8a7ea59","file":"DSC_9135.jpg","width":"2432","height":"1600","date":"2023:09:30 18:12:12","thumbnail":null,"size":297839},{"id":"34125e34-a635-4ecf-b220-bf9f02781098","file":"DSC_9133.jpg","width":"2432","height":"1600","date":"2023:09:30 18:12:01","thumbnail":null,"size":393020},{"id":"191d6d6c-ace9-4b14-863b-2e21c307c774","file":"DSC_9132.jpg","width":"2432","height":"1600","date":"2023:09:30 18:12:00","thumbnail":null,"size":396539},{"id":"b9097474-5a1d-47d2-8fc8-651d88c482a3","file":"DSC_9131.jpg","width":"2432","height":"1600","date":"2023:09:30 18:11:56","thumbnail":null,"size":383255},{"id":"edb82168-631a-4732-aaaf-15d504934178","file":"DSC_9130.jpg","width":"1053","height":"1600","date":"2023:09:30 18:11:15","thumbnail":null,"size":432959},{"id":"68ef6853-bcbc-452f-942d-76b566dbfcc2","file":"DSC_9129.jpg","width":"1053","height":"1600","date":"2023:09:30 18:11:12","thumbnail":null,"size":461520},{"id":"5bdac266-89bb-4c9e-9eb4-5cde580236d3","file":"DSC_9128.jpg","width":"1053","height":"1600","date":"2023:09:30 18:10:03","thumbnail":null,"size":394036},{"id":"25aa60af-0774-4138-bebb-a61030493039","file":"DSC_9127.jpg","width":"1053","height":"1600","date":"2023:09:30 18:10:01","thumbnail":null,"size":376234},{"id":"e0e10675-63ca-43f4-8eae-36313d18c267","file":"DSC_9126.jpg","width":"1053","height":"1600","date":"2023:09:30 18:09:58","thumbnail":null,"size":423110},{"id":"9f035cb2-6fc1-403a-9ede-3b31446eb585","file":"DSC_9125.jpg","width":"1053","height":"1600","date":"2023:09:30 18:09:55","thumbnail":null,"size":429666},{"id":"d3c9c2c8-fd05-44be-9c9f-3d8a6e8ddf7b","file":"DSC_9123.jpg","width":"1053","height":"1600","date":"2023:09:30 18:09:31","thumbnail":null,"size":423578},{"id":"33b234ef-fdc2-4b74-bf21-5f860cec9ffe","file":"DSC_9124.jpg","width":"1053","height":"1600","date":"2023:09:30 18:09:31","thumbnail":null,"size":484077},{"id":"24b4f4af-6fdb-4239-974f-406cb8b8c72b","file":"DSC_9122.jpg","width":"1053","height":"1600","date":"2023:09:30 18:09:30","thumbnail":null,"size":395697},{"id":"02d93087-0a97-4c0f-825e-d655d6db5208","file":"DSC_9121.jpg","width":"1053","height":"1600","date":"2023:09:30 18:09:21","thumbnail":null,"size":458582},{"id":"642229c3-3225-47f5-a3f3-f3d1d2aa4cdc","file":"DSC_9120.jpg","width":"1053","height":"1600","date":"2023:09:30 18:09:09","thumbnail":null,"size":403191},{"id":"6d2c7427-471d-4ad3-bd20-b25752a2fc21","file":"DSC_9119.jpg","width":"1053","height":"1600","date":"2023:09:30 18:09:08","thumbnail":null,"size":380152},{"id":"41d8b1e1-7abe-48c4-93eb-a7e2601b954b","file":"DSC_9118.jpg","width":"1053","height":"1600","date":"2023:09:30 18:09:04","thumbnail":null,"size":353651},{"id":"ef20055a-f8d1-4ad7-a257-f14794e1804c","file":"DSC_9117.jpg","width":"1053","height":"1600","date":"2023:09:30 18:09:03","thumbnail":null,"size":450208},{"id":"24ce29ed-5a90-4985-b034-72747733215a","file":"DSC_9116.jpg","width":"1053","height":"1600","date":"2023:09:30 18:08:43","thumbnail":null,"size":282755},{"id":"022424d6-b123-4e26-9aa0-91217344491a","file":"DSC_9115.jpg","width":"1053","height":"1600","date":"2023:09:30 18:08:42","thumbnail":null,"size":265053},{"id":"e8e78828-1f8a-4681-8f9c-ccb26f5ae085","file":"DSC_9114.jpg","width":"1053","height":"1600","date":"2023:09:30 18:04:57","thumbnail":null,"size":363888},{"id":"473141f4-6e56-4ca4-a479-f60097935e83","file":"DSC_9112.jpg","width":"1053","height":"1600","date":"2023:09:30 18:04:46","thumbnail":null,"size":320054},{"id":"560e8777-408b-4024-82ac-72608e10a0e0","file":"DSC_9113.jpg","width":"1053","height":"1600","date":"2023:09:30 18:04:46","thumbnail":null,"size":310277},{"id":"544b2649-2f4f-4cf1-a39c-9c56c299ab2a","file":"DSC_9111.jpg","width":"1053","height":"1600","date":"2023:09:30 18:04:45","thumbnail":null,"size":302687},{"id":"3bced962-218f-408c-b529-a80407d8229d","file":"DSC_9110.jpg","width":"1053","height":"1600","date":"2023:09:30 18:04:43","thumbnail":null,"size":317140},{"id":"e39347a4-1506-48f4-ae81-d33a5381ffdf","file":"DSC_9109.jpg","width":"1053","height":"1600","date":"2023:09:30 18:04:39","thumbnail":null,"size":320409},{"id":"24b17539-a4d6-4960-b57f-74bf1b8410ed","file":"DSC_9107.jpg","width":"1053","height":"1600","date":"2023:09:30 18:04:02","thumbnail":null,"size":333008},{"id":"deaec8a4-fce4-47bd-854b-8f28db5fdba8","file":"DSC_9106.jpg","width":"1053","height":"1600","date":"2023:09:30 18:04:00","thumbnail":null,"size":312607},{"id":"77037fac-2b82-4048-a4d2-8784ff0359e5","file":"DSC_9105.jpg","width":"1053","height":"1600","date":"2023:09:30 18:03:58","thumbnail":null,"size":312188},{"id":"e6d37e75-12a1-4611-a524-ec8bd9410363","file":"DSC_9103.jpg","width":"1053","height":"1600","date":"2023:09:30 18:03:44","thumbnail":null,"size":282103},{"id":"d7950b99-9141-475f-bff6-deab4a546a06","file":"DSC_9104.jpg","width":"1053","height":"1600","date":"2023:09:30 18:03:44","thumbnail":null,"size":277026},{"id":"7e5ca8a2-9cdd-4d20-89f1-aa36bb9e58f8","file":"DSC_9102.jpg","width":"1053","height":"1600","date":"2023:09:30 18:03:43","thumbnail":null,"size":284674},{"id":"fc4042fb-4f99-41e9-bd5d-2d4be77cf0a0","file":"DSC_9101.jpg","width":"1053","height":"1600","date":"2023:09:30 18:03:37","thumbnail":null,"size":275112},{"id":"8ce8d48d-64e7-477c-8c1b-c2de4fc6b524","file":"DSC_9099.jpg","width":"1053","height":"1600","date":"2023:09:30 18:03:36","thumbnail":null,"size":262737},{"id":"767406e5-26b9-42fd-bf21-9234ea0a1835","file":"DSC_9100.jpg","width":"1053","height":"1600","date":"2023:09:30 18:03:36","thumbnail":null,"size":282390},{"id":"04fbaca3-8cad-4ebe-a976-9363f73d7994","file":"DSC_9098.jpg","width":"1053","height":"1600","date":"2023:09:30 18:02:16","thumbnail":null,"size":469690},{"id":"14e43976-3b9c-4bd8-b049-7234bc17bac3","file":"DSC_9096.jpg","width":"1053","height":"1600","date":"2023:09:30 18:01:27","thumbnail":null,"size":569038},{"id":"1a319b77-e739-4537-bef0-8e37d471a41a","file":"DSC_9097.jpg","width":"1053","height":"1600","date":"2023:09:30 18:01:27","thumbnail":null,"size":554523},{"id":"f67c4a02-143f-41a8-ab09-6d12549bc335","file":"DSC_9095.jpg","width":"1053","height":"1600","date":"2023:09:30 18:01:26","thumbnail":null,"size":547040},{"id":"b15fce0e-18b4-4f42-89dd-db4a32f05a96","file":"DSC_9094.jpg","width":"1053","height":"1600","date":"2023:09:30 18:01:12","thumbnail":null,"size":289664},{"id":"3e8b170a-454e-4d85-a5d6-0f007d14aa88","file":"DSC_9093.jpg","width":"1053","height":"1600","date":"2023:09:30 18:01:11","thumbnail":null,"size":289840},{"id":"657fd28a-fc1c-464b-8319-7d2ba860b24a","file":"DSC_9092.jpg","width":"1053","height":"1600","date":"2023:09:30 18:00:53","thumbnail":null,"size":456958},{"id":"fefe394e-4d80-4e95-b95a-3333d694dc0c","file":"DSC_9091.jpg","width":"1053","height":"1600","date":"2023:09:30 18:00:51","thumbnail":null,"size":460298},{"id":"6c9571bc-a8ff-48f6-8e56-6f91d6295fa9","file":"DSC_9090.jpg","width":"1053","height":"1600","date":"2023:09:30 18:00:24","thumbnail":null,"size":451128},{"id":"93dded83-56c3-4532-a938-d1bc798c0696","file":"DSC_9089.jpg","width":"1053","height":"1600","date":"2023:09:30 17:58:31","thumbnail":null,"size":383166},{"id":"8dda9262-52e3-4fa3-a091-40464a619dca","file":"DSC_9088.jpg","width":"1053","height":"1600","date":"2023:09:30 17:58:26","thumbnail":null,"size":379547},{"id":"9d22e7fe-ea6e-4616-85d5-3a9f7ba9982f","file":"DSC_9087.jpg","width":"1053","height":"1600","date":"2023:09:30 17:58:18","thumbnail":null,"size":443646},{"id":"980d000a-95d9-48ea-98dd-53f3da1a3350","file":"DSC_9086.jpg","width":"1053","height":"1600","date":"2023:09:30 17:58:17","thumbnail":null,"size":439256},{"id":"4aab884d-47cc-4bb8-9bd5-27f9d6fe41bb","file":"DSC_9085.jpg","width":"1053","height":"1600","date":"2023:09:30 17:58:15","thumbnail":null,"size":433915},{"id":"c4ca1749-a529-4598-9d7f-db042477d91d","file":"DSC_9084.jpg","width":"1053","height":"1600","date":"2023:09:30 17:57:08","thumbnail":null,"size":642978},{"id":"3ad15ace-9062-488b-acb9-c4b7f6de7fda","file":"DSC_9082.jpg","width":"1053","height":"1600","date":"2023:09:30 17:57:07","thumbnail":null,"size":655504},{"id":"8dcafa69-74f5-43b8-b623-c15a19e0fa32","file":"DSC_9083.jpg","width":"1053","height":"1600","date":"2023:09:30 17:57:07","thumbnail":null,"size":652521},{"id":"6334ee8a-1fd7-451e-ba1e-e1f9f836e0ab","file":"DSC_9081.jpg","width":"1053","height":"1600","date":"2023:09:30 17:57:06","thumbnail":null,"size":680684},{"id":"a8015df3-095f-4ec9-8eba-c183f40f6280","file":"DSC_9080.jpg","width":"2432","height":"1600","date":"2023:09:30 17:56:01","thumbnail":null,"size":1149798},{"id":"faf97e36-d4a1-40e4-bd05-221be58aa405","file":"DSC_9078.jpg","width":"1053","height":"1600","date":"2023:09:30 17:55:30","thumbnail":null,"size":489786},{"id":"0afab972-f38d-4748-b64c-47e280e810c8","file":"DSC_9077.jpg","width":"1053","height":"1600","date":"2023:09:30 17:55:28","thumbnail":null,"size":544538},{"id":"a290dce6-eb15-41b6-8765-bbe2543a5557","file":"DSC_9076.jpg","width":"1053","height":"1600","date":"2023:09:30 17:55:18","thumbnail":null,"size":632353},{"id":"f964c1b3-32f5-4a4f-bfe3-9f365639fee7","file":"DSC_9075.jpg","width":"1053","height":"1600","date":"2023:09:30 17:54:47","thumbnail":null,"size":384335},{"id":"72ab71f9-5c8d-40d4-8850-f65c5d174092","file":"DSC_9074.jpg","width":"1053","height":"1600","date":"2023:09:30 17:54:46","thumbnail":null,"size":375621},{"id":"a65ef051-7a08-4f44-b7ed-ad4db874787a","file":"DSC_9073.jpg","width":"1053","height":"1600","date":"2023:09:30 17:54:38","thumbnail":null,"size":348768},{"id":"7d7ff367-8240-4ea4-a7e6-696969863982","file":"DSC_9071.jpg","width":"1053","height":"1600","date":"2023:09:30 17:54:37","thumbnail":null,"size":345286},{"id":"56500df7-1e75-4d2a-b811-c6a6640e78d7","file":"DSC_9072.jpg","width":"1053","height":"1600","date":"2023:09:30 17:54:37","thumbnail":null,"size":348347},{"id":"6188b04f-c6fb-4949-9cad-ad4c6e5e2ac6","file":"DSC_9070.jpg","width":"1053","height":"1600","date":"2023:09:30 17:54:14","thumbnail":null,"size":554360},{"id":"dd3caef6-eb6a-4fe9-9b76-46f664a3366d","file":"DSC_9068.jpg","width":"1053","height":"1600","date":"2023:09:30 17:54:13","thumbnail":null,"size":482366},{"id":"1c11be24-7de4-41ec-af8d-c31331f1b0ac","file":"DSC_9069.jpg","width":"1053","height":"1600","date":"2023:09:30 17:54:13","thumbnail":null,"size":565632},{"id":"872d3b11-c18c-4a3a-ae34-4567ab4d86dc","file":"DSC_9067.jpg","width":"1053","height":"1600","date":"2023:09:30 17:54:11","thumbnail":null,"size":482722},{"id":"9d41a2b7-c07a-45e1-9807-aaf31c4bef34","file":"DSC_9066.jpg","width":"1053","height":"1600","date":"2023:09:30 17:53:56","thumbnail":null,"size":365599},{"id":"8f16ee91-be6c-4106-a0ba-b3f01a057419","file":"DSC_9064.jpg","width":"1053","height":"1600","date":"2023:09:30 17:53:20","thumbnail":null,"size":330650},{"id":"207e8c23-eeba-4e4a-86c8-c6281969c22c","file":"DSC_9062.jpg","width":"1053","height":"1600","date":"2023:09:30 17:53:19","thumbnail":null,"size":304322},{"id":"4400ec61-b21d-45c7-83a1-feaa73f997f1","file":"DSC_9063.jpg","width":"1053","height":"1600","date":"2023:09:30 17:53:19","thumbnail":null,"size":315772},{"id":"00ec33ce-933f-4642-858e-6905eec739ae","file":"DSC_9061.jpg","width":"1053","height":"1600","date":"2023:09:30 17:53:17","thumbnail":null,"size":304132},{"id":"b0e1a084-ff36-4339-871c-9503478ebdd5","file":"DSC_9060.jpg","width":"2432","height":"1600","date":"2023:09:30 17:53:12","thumbnail":null,"size":473709},{"id":"b2353a80-5a2f-4630-9425-10e3c469756b","file":"DSC_9059.jpg","width":"2432","height":"1600","date":"2023:09:30 17:53:08","thumbnail":null,"size":469358},{"id":"c7e141de-a09f-4d06-81f7-689b52cdfd1c","file":"DSC_9058.jpg","width":"2432","height":"1600","date":"2023:09:30 17:53:05","thumbnail":null,"size":457742},{"id":"aa2957dd-aea6-4466-b011-6d6a059bd496","file":"DSC_9056.jpg","width":"1053","height":"1600","date":"2023:09:30 17:53:00","thumbnail":null,"size":342895},{"id":"69f9aa67-984f-4d5a-9c60-f08cd2207a10","file":"DSC_9057.jpg","width":"1053","height":"1600","date":"2023:09:30 17:53:00","thumbnail":null,"size":343650},{"id":"b0dc51c1-a94c-4fb9-b846-5b2d3db395fd","file":"DSC_9053.jpg","width":"1053","height":"1600","date":"2023:09:30 17:52:59","thumbnail":null,"size":346529},{"id":"0773d49c-e699-4e1a-97ff-623a2419ce7d","file":"DSC_9054.jpg","width":"1053","height":"1600","date":"2023:09:30 17:52:59","thumbnail":null,"size":342908},{"id":"0f24ab6e-b7a6-48a2-bdd5-8221e4cb1c43","file":"DSC_9055.jpg","width":"1053","height":"1600","date":"2023:09:30 17:52:59","thumbnail":null,"size":345227},{"id":"2ded4f65-9316-431a-9a4b-96a1f4de85ae","file":"DSC_9052.jpg","width":"1053","height":"1600","date":"2023:09:30 17:52:58","thumbnail":null,"size":206439},{"id":"2f4d47d8-4525-40c1-9082-e7377621a65f","file":"DSC_9050.jpg","width":"1053","height":"1600","date":"2023:09:30 17:51:52","thumbnail":null,"size":644254},{"id":"8a0a7747-7eaa-43b8-9bcb-5ad2b0854690","file":"DSC_9048.jpg","width":"1053","height":"1600","date":"2023:09:30 17:51:10","thumbnail":null,"size":680847},{"id":"4783383a-df16-41bd-afdf-53f617f39062","file":"DSC_9047.jpg","width":"1053","height":"1600","date":"2023:09:30 17:51:08","thumbnail":null,"size":671859},{"id":"329689af-3f41-4474-9d53-fae775e745a4","file":"DSC_9046.jpg","width":"2432","height":"1600","date":"2023:09:30 17:50:44","thumbnail":null,"size":1477843},{"id":"07b5dfe8-535f-42f7-b4a4-9c2a425d14be","file":"DSC_9045.jpg","width":"2432","height":"1600","date":"2023:09:30 17:50:43","thumbnail":null,"size":1502566},{"id":"fd66889b-786d-4b0f-baf1-2d12c4c6ee68","file":"DSC_9044.jpg","width":"1053","height":"1600","date":"2023:09:30 17:50:34","thumbnail":null,"size":667835},{"id":"1899fc79-8ba5-42e9-873e-c91ef571ea2a","file":"DSC_9043.jpg","width":"1053","height":"1600","date":"2023:09:30 17:50:32","thumbnail":null,"size":598934},{"id":"93b0fe84-9ad2-40b1-8059-2466dd304ead","file":"DSC_9042.jpg","width":"1053","height":"1600","date":"2023:09:30 17:50:28","thumbnail":null,"size":617389},{"id":"72d0a9c3-c034-4513-9a98-b39dc316621b","file":"DSC_9041.jpg","width":"1053","height":"1600","date":"2023:09:30 17:50:19","thumbnail":null,"size":506624},{"id":"3d3f4b0e-fa85-40da-846b-8318fa245783","file":"DSC_9040.jpg","width":"1053","height":"1600","date":"2023:09:30 17:50:08","thumbnail":null,"size":679429},{"id":"7da89f5d-8667-4fc3-86c0-e01f0a01d1a6","file":"DSC_9038.jpg","width":"1053","height":"1600","date":"2023:09:30 17:48:25","thumbnail":null,"size":580276},{"id":"a761741c-9b7b-4003-8aa7-a7855c995b1a","file":"DSC_9039.jpg","width":"1053","height":"1600","date":"2023:09:30 17:48:25","thumbnail":null,"size":656455},{"id":"41f47201-ea05-41e5-9175-bd1128d926a4","file":"DSC_9036.jpg","width":"1053","height":"1600","date":"2023:09:30 17:48:24","thumbnail":null,"size":612569},{"id":"3065ee7c-d20a-49b6-94fe-839a2d2786fd","file":"DSC_9037.jpg","width":"1053","height":"1600","date":"2023:09:30 17:48:24","thumbnail":null,"size":585028},{"id":"691d1a5a-3884-4160-a6a9-8e8efe19dcdf","file":"DSC_9035.jpg","width":"1053","height":"1600","date":"2023:09:30 17:48:22","thumbnail":null,"size":580561},{"id":"9b6eba6b-4c1d-4f09-a198-18d622e222b4","file":"DSC_9034.jpg","width":"2432","height":"1600","date":"2023:09:30 17:47:52","thumbnail":null,"size":553407},{"id":"b10f8226-760c-4b90-93c4-74c832a7e2d3","file":"DSC_9033.jpg","width":"2432","height":"1600","date":"2023:09:30 17:47:51","thumbnail":null,"size":556678},{"id":"952eeed7-fc7d-4c4a-bc8d-61c3f14ae202","file":"DSC_9032.jpg","width":"2432","height":"1600","date":"2023:09:30 17:47:50","thumbnail":null,"size":550294},{"id":"074a2c81-f235-4b17-9d76-817bdae148e4","file":"DSC_9030.jpg","width":"2432","height":"1600","date":"2023:09:30 17:47:36","thumbnail":null,"size":535843},{"id":"c282540e-3dde-42e0-8421-df12a609f53a","file":"DSC_9031.jpg","width":"2432","height":"1600","date":"2023:09:30 17:47:36","thumbnail":null,"size":565797},{"id":"c4999744-129f-4605-a05a-5df58b272e80","file":"DSC_9029.jpg","width":"2432","height":"1600","date":"2023:09:30 17:47:35","thumbnail":null,"size":532168},{"id":"142ffa6e-23ee-4369-82e5-1d629c09bc4f","file":"DSC_9028.jpg","width":"2432","height":"1600","date":"2023:09:30 17:47:31","thumbnail":null,"size":496030},{"id":"3fa4e908-6479-4c7e-bc78-25768f14c169","file":"DSC_9027.jpg","width":"2432","height":"1600","date":"2023:09:30 17:47:30","thumbnail":null,"size":452184},{"id":"aeb293c8-2c9d-4c8b-a54f-3e775ce1c0c8","file":"DSC_9026.jpg","width":"2432","height":"1600","date":"2023:09:30 17:47:29","thumbnail":null,"size":450853},{"id":"ecea86bc-b846-4555-adb1-4fa7b663ab2f","file":"DSC_9024.jpg","width":"2432","height":"1600","date":"2023:09:30 17:46:37","thumbnail":null,"size":1013423},{"id":"b9863993-f01a-4d50-8b15-739ffae766e6","file":"DSC_9023.jpg","width":"2432","height":"1600","date":"2023:09:30 17:46:23","thumbnail":null,"size":969154},{"id":"fea08e8c-0b64-49af-bec4-add2310aab40","file":"DSC_9021.jpg","width":"2432","height":"1600","date":"2023:09:30 17:46:08","thumbnail":null,"size":529949},{"id":"54cfd730-edcb-4f4f-99c5-57adac916859","file":"DSC_9020.jpg","width":"2432","height":"1600","date":"2023:09:30 17:46:07","thumbnail":null,"size":528006},{"id":"2f8bacb7-e33f-48fb-a282-2d6c63936dc6","file":"DSC_9018.jpg","width":"2432","height":"1600","date":"2023:09:30 17:45:11","thumbnail":null,"size":1515448},{"id":"538b4280-4ad4-42c9-80a7-e79a331d6bb8","file":"DSC_9017.jpg","width":"2432","height":"1600","date":"2023:09:30 17:45:09","thumbnail":null,"size":1322697},{"id":"dd721438-73c9-4cf8-85ba-7041d2ab6762","file":"DSC_9016.jpg","width":"1053","height":"1600","date":"2023:09:30 17:44:49","thumbnail":null,"size":545695},{"id":"cd8c6649-7c3f-4714-bfba-cd54954f2457","file":"DSC_9015.jpg","width":"1053","height":"1600","date":"2023:09:30 17:44:48","thumbnail":null,"size":713053},{"id":"c7e6abb6-7dd4-4dc7-a027-f58264bef6a4","file":"DSC_9013.jpg","width":"1053","height":"1600","date":"2023:09:30 17:42:00","thumbnail":null,"size":679133},{"id":"18bd2291-6fae-4524-bb82-d05f2f22af02","file":"DSC_9011.jpg","width":"1053","height":"1600","date":"2023:09:30 17:41:59","thumbnail":null,"size":681026},{"id":"aaa17e3e-dacd-4f27-8f86-b9ef665ef916","file":"DSC_9012.jpg","width":"1053","height":"1600","date":"2023:09:30 17:41:59","thumbnail":null,"size":492800},{"id":"06c49266-344c-47b5-a75f-1b69f7fbacf7","file":"DSC_9010.jpg","width":"1053","height":"1600","date":"2023:09:30 17:41:57","thumbnail":null,"size":680718},{"id":"458ade20-929e-4b55-a8b9-7d44b38199b6","file":"DSC_9009.jpg","width":"1053","height":"1600","date":"2023:09:30 17:41:13","thumbnail":null,"size":353058},{"id":"3a5c1dd2-6596-483c-b72d-64fc4304ee52","file":"DSC_9008.jpg","width":"1053","height":"1600","date":"2023:09:30 17:39:16","thumbnail":null,"size":400157},{"id":"c99f84c9-1f40-4d51-bd1b-ab14b2944d4a","file":"DSC_9007.jpg","width":"1053","height":"1600","date":"2023:09:30 17:39:14","thumbnail":null,"size":408374},{"id":"9dc8d652-bd4f-4f0a-944e-80461dee2bb9","file":"DSC_9005.jpg","width":"1053","height":"1600","date":"2023:09:30 17:38:44","thumbnail":null,"size":630864},{"id":"9bebde76-8f02-4d14-8111-bd39949da176","file":"DSC_9006.jpg","width":"1053","height":"1600","date":"2023:09:30 17:38:44","thumbnail":null,"size":622453},{"id":"7fd49ecc-9099-4a58-8e24-7bcdf021e54c","file":"DSC_9004.jpg","width":"1053","height":"1600","date":"2023:09:30 17:38:43","thumbnail":null,"size":329184},{"id":"57865351-2ffb-40f6-aec9-713f9ed0ae31","file":"DSC_9003.jpg","width":"1053","height":"1600","date":"2023:09:30 17:38:24","thumbnail":null,"size":483566},{"id":"269ce173-6c7f-4f40-a4c3-bed94863972c","file":"DSC_9002.jpg","width":"1053","height":"1600","date":"2023:09:30 17:38:18","thumbnail":null,"size":573128},{"id":"f6b79f65-7e45-489b-9b19-feedde9da65e","file":"DSC_9001.jpg","width":"1053","height":"1600","date":"2023:09:30 17:35:31","thumbnail":null,"size":404942},{"id":"7d254486-81e5-4d3e-8690-15973b02b2a7","file":"DSC_9000.jpg","width":"1053","height":"1600","date":"2023:09:30 17:35:28","thumbnail":null,"size":384212},{"id":"f10352c0-6d39-4819-a50f-34b30b3548f0","file":"DSC_8999.jpg","width":"2432","height":"1600","date":"2023:09:30 17:35:15","thumbnail":null,"size":1444586},{"id":"575883ce-52fa-4ee2-8f44-af8fcaeb16d5","file":"DSC_8998.jpg","width":"2432","height":"1600","date":"2023:09:30 17:35:05","thumbnail":null,"size":1062760},{"id":"637fa947-5a86-4de9-93f1-b3875aa19fce","file":"DSC_8997.jpg","width":"2432","height":"1600","date":"2023:09:30 17:35:03","thumbnail":null,"size":1250955},{"id":"4eee8166-e789-4957-a564-f3ffff8377df","file":"DSC_8996.jpg","width":"1053","height":"1600","date":"2023:09:30 17:34:58","thumbnail":null,"size":368006},{"id":"2d87ada8-c3b5-47c0-83a7-45f3ec3e9d28","file":"DSC_8993.jpg","width":"1053","height":"1600","date":"2023:09:30 17:34:04","thumbnail":null,"size":695637},{"id":"5b4fefa9-57c1-4ad3-89d7-ee4f792619aa","file":"DSC_8994.jpg","width":"1053","height":"1600","date":"2023:09:30 17:34:04","thumbnail":null,"size":698885},{"id":"fe9c2faf-0c95-474d-a9d6-0f2510d56eec","file":"DSC_8995.jpg","width":"1053","height":"1600","date":"2023:09:30 17:34:04","thumbnail":null,"size":697867},{"id":"82504a2f-8b68-46f3-982b-b946d8be6046","file":"DSC_8992.jpg","width":"1053","height":"1600","date":"2023:09:30 17:34:03","thumbnail":null,"size":697743},{"id":"dc58ffdd-7465-4830-8b81-163679384859","file":"DSC_8991.jpg","width":"1053","height":"1600","date":"2023:09:30 17:33:06","thumbnail":null,"size":669518},{"id":"54eba6f4-8013-4610-8cce-e211de310f44","file":"DSC_8989.jpg","width":"1053","height":"1600","date":"2023:09:30 17:30:06","thumbnail":null,"size":315400},{"id":"47a1e559-0955-46b3-b6f0-946298a459d3","file":"DSC_8990.jpg","width":"1053","height":"1600","date":"2023:09:30 17:30:06","thumbnail":null,"size":310013},{"id":"1b190bdb-a351-41fd-9e2d-e64bc15ed33b","file":"DSC_8988.jpg","width":"1053","height":"1600","date":"2023:09:30 17:30:05","thumbnail":null,"size":313320},{"id":"5ff1b479-e288-41c1-9ad9-3e72c04797a5","file":"DSC_8987.jpg","width":"1053","height":"1600","date":"2023:09:30 17:30:04","thumbnail":null,"size":307188},{"id":"66d2cc84-4c24-44b6-ac97-e46916a0304d","file":"DSC_8986.jpg","width":"1053","height":"1600","date":"2023:09:30 17:30:03","thumbnail":null,"size":306128},{"id":"f1f3efe6-a388-4426-ba22-d330678c4d86","file":"DSC_8985.jpg","width":"1053","height":"1600","date":"2023:09:30 17:29:51","thumbnail":null,"size":285114},{"id":"1a60ae90-f0ed-4b43-a87e-4dc5c22fe6e3","file":"DSC_8984.jpg","width":"1053","height":"1600","date":"2023:09:30 17:29:48","thumbnail":null,"size":299685},{"id":"0de89020-8fe7-427b-a199-b73ebff787b3","file":"DSC_8983.jpg","width":"1053","height":"1600","date":"2023:09:30 17:29:42","thumbnail":null,"size":271449},{"id":"ae0d4659-7ddb-4ef2-9edf-9eee9d998c80","file":"DSC_8982.jpg","width":"1053","height":"1600","date":"2023:09:30 17:27:58","thumbnail":null,"size":669982},{"id":"7c78b67d-1947-4312-b8dc-3e182bcd50d9","file":"DSC_8981.jpg","width":"1053","height":"1600","date":"2023:09:30 17:27:57","thumbnail":null,"size":537357},{"id":"6129a37c-31d1-4681-b6bb-34563dbe584b","file":"DSC_8980.jpg","width":"1053","height":"1600","date":"2023:09:30 17:27:45","thumbnail":null,"size":696897},{"id":"6d068871-5551-49ee-ad8a-e75732e54338","file":"DSC_8979.jpg","width":"1053","height":"1600","date":"2023:09:30 17:27:44","thumbnail":null,"size":713902},{"id":"811c04af-10a8-47ed-90d9-c2e6c9ed0f5d","file":"DSC_8977.jpg","width":"1053","height":"1600","date":"2023:09:30 17:27:16","thumbnail":null,"size":353102},{"id":"1324c350-6d4d-444e-b37e-7e9232654613","file":"DSC_8978.jpg","width":"1053","height":"1600","date":"2023:09:30 17:27:16","thumbnail":null,"size":343533},{"id":"a4d9bb36-1cae-45aa-b9ba-81406cb68dd5","file":"DSC_8976.jpg","width":"1053","height":"1600","date":"2023:09:30 17:27:14","thumbnail":null,"size":341785},{"id":"78a7071d-4af2-4a17-b1c2-91d00b55695a","file":"DSC_8974.jpg","width":"1053","height":"1600","date":"2023:09:30 17:24:09","thumbnail":null,"size":506422},{"id":"741d8b53-62a3-4edd-8b1e-b6c234aec131","file":"DSC_8975.jpg","width":"1053","height":"1600","date":"2023:09:30 17:24:09","thumbnail":null,"size":539200},{"id":"1cdeeeed-8f02-45e2-926e-ee88fdd587c6","file":"DSC_8973.jpg","width":"1053","height":"1600","date":"2023:09:30 17:24:08","thumbnail":null,"size":527831},{"id":"f3cd6a93-6ed0-4abc-acd7-bcf3173ce826","file":"DSC_8972.jpg","width":"1053","height":"1600","date":"2023:09:30 17:23:56","thumbnail":null,"size":313190},{"id":"145c1a1c-f911-4254-860b-731fd60b18db","file":"DSC_8971.jpg","width":"1053","height":"1600","date":"2023:09:30 17:23:51","thumbnail":null,"size":305130},{"id":"01dc0c23-03fe-428e-b55f-b7573d8857af","file":"DSC_8970.jpg","width":"1053","height":"1600","date":"2023:09:30 17:23:50","thumbnail":null,"size":303364},{"id":"f57566ae-31ca-4966-af0f-ae53e8411b27","file":"DSC_8969.jpg","width":"1053","height":"1600","date":"2023:09:30 17:23:46","thumbnail":null,"size":378276},{"id":"021a8316-1bd9-4a33-86e1-bc66920d5d0b","file":"DSC_8968.jpg","width":"1053","height":"1600","date":"2023:09:30 17:23:44","thumbnail":null,"size":354060},{"id":"0882594f-4ac7-423e-81e4-3fa58250254a","file":"DSC_8967.jpg","width":"1053","height":"1600","date":"2023:09:30 17:23:43","thumbnail":null,"size":363414},{"id":"29a17c28-db3a-41e6-a76a-9f42d3c7ca33","file":"DSC_8966.jpg","width":"1053","height":"1600","date":"2023:09:30 17:23:36","thumbnail":null,"size":360397},{"id":"addd4947-5adf-45ae-9197-e84c0423f719","file":"DSC_8965.jpg","width":"1053","height":"1600","date":"2023:09:30 17:23:34","thumbnail":null,"size":349702},{"id":"3671f57d-51c1-4094-9436-318dfa8edb68","file":"DSC_8964.jpg","width":"1053","height":"1600","date":"2023:09:30 17:23:32","thumbnail":null,"size":318740},{"id":"52661c21-7131-468a-bdeb-6eab87130dcb","file":"DSC_8963.jpg","width":"1053","height":"1600","date":"2023:09:30 17:23:31","thumbnail":null,"size":308683},{"id":"fcff2886-a580-42ce-a2f4-e499bc146cf5","file":"DSC_8961.jpg","width":"1053","height":"1600","date":"2023:09:30 17:22:56","thumbnail":null,"size":474773},{"id":"286d41d5-da5c-4fae-8784-abda3df66092","file":"DSC_8962.jpg","width":"1053","height":"1600","date":"2023:09:30 17:22:56","thumbnail":null,"size":483613},{"id":"13e1d371-21bb-499b-b79e-6657f9239538","file":"DSC_8960.jpg","width":"1053","height":"1600","date":"2023:09:30 17:22:55","thumbnail":null,"size":458798},{"id":"414127fb-5691-4791-8e70-f5c866b4e393","file":"DSC_8959.jpg","width":"1053","height":"1600","date":"2023:09:30 17:22:23","thumbnail":null,"size":333347},{"id":"ac0cbce1-2e23-4009-9ec9-55b1b1f66ad6","file":"DSC_8958.jpg","width":"1053","height":"1600","date":"2023:09:30 17:22:22","thumbnail":null,"size":319471},{"id":"306be646-2dc5-4249-9696-09252bdf575e","file":"DSC_8956.jpg","width":"1053","height":"1600","date":"2023:09:30 17:22:13","thumbnail":null,"size":335988},{"id":"1055df6d-adce-412c-9934-88f2ebf37254","file":"DSC_8957.jpg","width":"1053","height":"1600","date":"2023:09:30 17:22:13","thumbnail":null,"size":332631},{"id":"cd7abf49-3068-4f66-9f47-8d6ab6cea601","file":"DSC_8955.jpg","width":"1053","height":"1600","date":"2023:09:30 17:22:11","thumbnail":null,"size":314903},{"id":"a848fc1e-d864-48df-b15c-65c8c5a34779","file":"DSC_8952.jpg","width":"1053","height":"1600","date":"2023:09:30 17:21:38","thumbnail":null,"size":487149},{"id":"78ac68d2-da51-44ae-b4e7-a0b7b967f91c","file":"DSC_8953.jpg","width":"1053","height":"1600","date":"2023:09:30 17:21:38","thumbnail":null,"size":487281},{"id":"d5d01c33-1942-4551-b5df-cf0834fe2c7c","file":"DSC_8954.jpg","width":"1053","height":"1600","date":"2023:09:30 17:21:38","thumbnail":null,"size":488309},{"id":"24820f73-9bdf-436b-a5ec-0a3218ca168c","file":"DSC_8951.jpg","width":"1053","height":"1600","date":"2023:09:30 17:21:32","thumbnail":null,"size":509600},{"id":"7e49c170-1390-4ce5-8b43-744b920f0a52","file":"DSC_8950.jpg","width":"1053","height":"1600","date":"2023:09:30 17:21:31","thumbnail":null,"size":516960},{"id":"bda1ea90-bdc3-4fa5-9319-72843c624b77","file":"DSC_8949.jpg","width":"2432","height":"1600","date":"2023:09:30 17:20:29","thumbnail":null,"size":1033855},{"id":"5f42e2b5-b3cb-4e86-9830-c2cb6037be81","file":"DSC_8948.jpg","width":"1053","height":"1600","date":"2023:09:30 17:18:50","thumbnail":null,"size":699460},{"id":"8a46ce8e-fd9a-4ab2-957a-e9da0641867f","file":"DSC_8947.jpg","width":"1053","height":"1600","date":"2023:09:30 17:18:48","thumbnail":null,"size":647108},{"id":"68b7fa59-b354-41fd-9ee1-f937864dd869","file":"DSC_8946.jpg","width":"2432","height":"1600","date":"2023:09:30 17:18:10","thumbnail":null,"size":713794},{"id":"faad7d2c-68fc-4b7e-843b-ef2802496031","file":"DSC_8945.jpg","width":"1053","height":"1600","date":"2023:09:30 17:16:57","thumbnail":null,"size":359212},{"id":"b8f03f7b-0046-4ce5-8ace-82e472cd10ac","file":"DSC_8944.jpg","width":"1053","height":"1600","date":"2023:09:30 17:16:42","thumbnail":null,"size":351698},{"id":"57e50180-9769-463b-82d0-974f3babe114","file":"DSC_8943.jpg","width":"1053","height":"1600","date":"2023:09:30 17:15:56","thumbnail":null,"size":348962},{"id":"a8b47190-cb28-4c2c-955e-a223f173acd2","file":"DSC_8942.jpg","width":"1053","height":"1600","date":"2023:09:30 17:15:53","thumbnail":null,"size":341257},{"id":"e48336f5-28ba-42db-87e9-b8ade42c8162","file":"DSC_8941.jpg","width":"2432","height":"1600","date":"2023:09:30 17:15:19","thumbnail":null,"size":623313},{"id":"e4d92ddf-07eb-436e-811c-96f28ad1e67b","file":"DSC_8940.jpg","width":"2432","height":"1600","date":"2023:09:30 17:15:17","thumbnail":null,"size":637544},{"id":"186ddfcb-b6dd-4789-9506-5d2accb52dc3","file":"DSC_8939.jpg","width":"2432","height":"1600","date":"2023:09:30 17:15:14","thumbnail":null,"size":606488},{"id":"289d05c5-6afb-4622-bd19-9ab05398690e","file":"DSC_8938.jpg","width":"2432","height":"1600","date":"2023:09:30 17:14:53","thumbnail":null,"size":632807},{"id":"7224577a-33c1-4b71-9651-b894942e525a","file":"DSC_8937.jpg","width":"1053","height":"1600","date":"2023:09:30 17:14:48","thumbnail":null,"size":318294},{"id":"f48cc2e2-9a78-4b06-85ff-5dd57f13bd91","file":"DSC_8936.jpg","width":"1053","height":"1600","date":"2023:09:30 17:14:46","thumbnail":null,"size":308654},{"id":"879b7896-98f3-423f-81ab-b5a9cfbdf879","file":"DSC_8935.jpg","width":"2432","height":"1600","date":"2023:09:30 17:14:17","thumbnail":null,"size":725607},{"id":"9ecbdf62-5d83-4302-9ec0-bf9a32e95b3c","file":"DSC_8934.jpg","width":"1053","height":"1600","date":"2023:09:30 17:13:55","thumbnail":null,"size":322365},{"id":"c59d6a45-98d8-42b2-aa9f-1659255b4787","file":"DSC_8933.jpg","width":"1053","height":"1600","date":"2023:09:30 17:13:54","thumbnail":null,"size":358424},{"id":"1fd2c0f7-218c-48f7-a98d-e6cece12971a","file":"DSC_8932.jpg","width":"1053","height":"1600","date":"2023:09:30 17:13:44","thumbnail":null,"size":441537},{"id":"b2778b9a-4f58-4f3d-9cc1-149115cef22d","file":"DSC_8931.jpg","width":"1053","height":"1600","date":"2023:09:30 17:13:43","thumbnail":null,"size":433030},{"id":"07f78bd0-2dfa-4f7f-b1ff-0e379bcc9253","file":"DSC_8930.jpg","width":"2432","height":"1600","date":"2023:09:30 17:13:09","thumbnail":null,"size":1046019},{"id":"27055b88-a810-416d-8a53-910ff5087ee6","file":"DSC_8929.jpg","width":"2432","height":"1600","date":"2023:09:30 17:12:27","thumbnail":null,"size":642137},{"id":"dd43cb6b-7a21-4ad4-a7dd-40d5308f483f","file":"DSC_8928.jpg","width":"2432","height":"1600","date":"2023:09:30 17:11:51","thumbnail":null,"size":681856},{"id":"b99e560c-ea27-466f-8c36-944bd6dc92c9","file":"DSC_8927.jpg","width":"2432","height":"1600","date":"2023:09:30 17:11:23","thumbnail":null,"size":874975},{"id":"55782cbe-39d5-4a79-a855-34d5c754669b","file":"DSC_8926.jpg","width":"2432","height":"1600","date":"2023:09:30 17:11:02","thumbnail":null,"size":662034},{"id":"d07d411a-485f-48bf-b079-c676e5946538","file":"DSC_8925.jpg","width":"1053","height":"1600","date":"2023:09:30 17:10:27","thumbnail":null,"size":453187},{"id":"e626751f-32f4-420e-bd6b-ba64752281fc","file":"DSC_8924.jpg","width":"2432","height":"1600","date":"2023:09:30 17:10:02","thumbnail":null,"size":874321},{"id":"e977bd28-82d8-4d96-ad6c-afe0ef9d36a7","file":"DSC_8923.jpg","width":"2432","height":"1600","date":"2023:09:30 17:09:51","thumbnail":null,"size":812368},{"id":"33e2ef52-9061-4c65-b1db-0102f4ed5155","file":"DSC_8922.jpg","width":"1053","height":"1600","date":"2023:09:30 17:09:21","thumbnail":null,"size":484656},{"id":"1e688758-0470-41db-82e5-33e9659d765a","file":"DSC_8921.jpg","width":"2432","height":"1600","date":"2023:09:30 17:09:08","thumbnail":null,"size":1314290},{"id":"27ebdb48-bf93-4ed1-ac7a-94952ba884a2","file":"DSC_8920.jpg","width":"1053","height":"1600","date":"2023:09:30 17:08:06","thumbnail":null,"size":772477},{"id":"41b8f156-ab62-4652-b4ca-a18aa26bf57b","file":"DSC_8919.jpg","width":"1053","height":"1600","date":"2023:09:30 17:07:56","thumbnail":null,"size":706989},{"id":"94c285bc-23ef-4cae-b0bf-b843601686cf","file":"DSC_8918.jpg","width":"1053","height":"1600","date":"2023:09:30 17:06:07","thumbnail":null,"size":640627},{"id":"f4ebe326-2289-4fd8-b3e9-a23e69f13440","file":"DSC_8917.jpg","width":"1053","height":"1600","date":"2023:09:30 17:04:51","thumbnail":null,"size":431127},{"id":"4d489e8c-66cf-4197-b5ec-01464512d1e7","file":"DSC_8916.jpg","width":"1053","height":"1600","date":"2023:09:30 17:04:38","thumbnail":null,"size":532043},{"id":"2c0a3e01-eaa1-4af6-a038-f6c1eb2418e8","file":"DSC_8915.jpg","width":"1053","height":"1600","date":"2023:09:30 17:04:18","thumbnail":null,"size":434045},{"id":"172e0b78-f361-4cca-9220-87f8563736b5","file":"DSC_8914.jpg","width":"1053","height":"1600","date":"2023:09:30 17:04:05","thumbnail":null,"size":581806},{"id":"5ba4042f-7b57-4eeb-a435-ead8bb0859c6","file":"DSC_8913.jpg","width":"1053","height":"1600","date":"2023:09:30 17:03:59","thumbnail":null,"size":559404},{"id":"c81ab6ce-04b1-435d-b8b3-4b68cc7f16f0","file":"DSC_8912.jpg","width":"1053","height":"1600","date":"2023:09:30 17:03:14","thumbnail":null,"size":524860},{"id":"1118a112-c9f7-4e05-b3f5-f9bb94e82d74","file":"DSC_8911.jpg","width":"1053","height":"1600","date":"2023:09:30 17:03:09","thumbnail":null,"size":513976},{"id":"73e6ccd7-148c-40d3-b4ea-cd9ea5861330","file":"DSC_8910.jpg","width":"1053","height":"1600","date":"2023:09:30 17:03:07","thumbnail":null,"size":431733},{"id":"04a4a4e5-6ce8-42df-b686-9bfc665f8e00","file":"DSC_8909.jpg","width":"1053","height":"1600","date":"2023:09:30 17:03:06","thumbnail":null,"size":448815},{"id":"12e7932a-08b3-4f66-aff5-0a7d8262f749","file":"DSC_8908.jpg","width":"1053","height":"1600","date":"2023:09:30 17:03:03","thumbnail":null,"size":494376},{"id":"d5d46f11-ee11-42ad-9834-8462ba407c41","file":"DSC_8907.jpg","width":"1053","height":"1600","date":"2023:09:30 17:02:57","thumbnail":null,"size":349416},{"id":"c48e9503-7560-47ca-b389-17f444fc50db","file":"DSC_8906.jpg","width":"1053","height":"1600","date":"2023:09:30 17:02:50","thumbnail":null,"size":381748},{"id":"8ef7a1da-aa6f-4389-ac84-938a1962e8f7","file":"DSC_8905.jpg","width":"2432","height":"1600","date":"2023:09:30 17:02:38","thumbnail":null,"size":652347},{"id":"b74a55b2-34e4-4569-8fe1-ee5f1173ff00","file":"DSC_8904.jpg","width":"2432","height":"1600","date":"2023:09:30 17:02:36","thumbnail":null,"size":635194},{"id":"7cd94467-c6fd-4882-83d6-d9e6b00248cd","file":"DSC_8903.jpg","width":"2432","height":"1600","date":"2023:09:30 17:02:33","thumbnail":null,"size":614836},{"id":"a713fff3-74dc-444b-a799-8f115840c60f","file":"DSC_8901.jpg","width":"2432","height":"1600","date":"2023:09:30 17:02:03","thumbnail":null,"size":849184},{"id":"10f74f97-f314-4b82-b4af-70e2a70475e9","file":"DSC_8900.jpg","width":"1053","height":"1600","date":"2023:09:30 17:01:40","thumbnail":null,"size":727389},{"id":"9f55f201-0490-4d11-aea7-9d5e54a8151f","file":"DSC_8899.jpg","width":"1053","height":"1600","date":"2023:09:30 17:01:38","thumbnail":null,"size":720746},{"id":"6579d772-b3d3-4871-b2b2-4b68c610bfbf","file":"DSC_8898.jpg","width":"1053","height":"1600","date":"2023:09:30 17:01:30","thumbnail":null,"size":695593},{"id":"97d9fd98-9b80-43b2-901e-c5a16fd6eee5","file":"DSC_8897.jpg","width":"1053","height":"1600","date":"2023:09:30 17:01:13","thumbnail":null,"size":671314},{"id":"5d8c9f4b-8071-4b9f-91be-441a96386ee7","file":"DSC_8896.jpg","width":"1053","height":"1600","date":"2023:09:30 17:00:42","thumbnail":null,"size":276023},{"id":"da607db0-3ca9-440f-a36d-409e6a77507b","file":"DSC_8895.jpg","width":"1053","height":"1600","date":"2023:09:30 17:00:40","thumbnail":null,"size":273721},{"id":"961240db-18d3-4df0-ad7d-49f527aaac72","file":"DSC_8893.jpg","width":"1053","height":"1600","date":"2023:09:30 17:00:14","thumbnail":null,"size":299456},{"id":"3634fb2a-c324-45e2-9f9a-33aa0606af6a","file":"DSC_8894.jpg","width":"1053","height":"1600","date":"2023:09:30 17:00:14","thumbnail":null,"size":279857},{"id":"adad53b2-c7bd-4c02-893e-d67f9de5f435","file":"DSC_8892.jpg","width":"1053","height":"1600","date":"2023:09:30 17:00:12","thumbnail":null,"size":273349},{"id":"555036e7-fb17-4dc8-a672-117f80751652","file":"DSC_8891.jpg","width":"1053","height":"1600","date":"2023:09:30 17:00:11","thumbnail":null,"size":294877},{"id":"f23d505d-8a77-4ace-902d-a7b1e663370b","file":"DSC_8890.jpg","width":"2432","height":"1600","date":"2023:09:30 16:59:49","thumbnail":null,"size":792482},{"id":"9feb3a1b-e1d5-4f69-9c2e-498477570e73","file":"DSC_8889.jpg","width":"2432","height":"1600","date":"2023:09:30 16:59:48","thumbnail":null,"size":772761},{"id":"0e17761f-60e9-4baf-9c38-d7cab781dd05","file":"DSC_8888.jpg","width":"2432","height":"1600","date":"2023:09:30 16:59:47","thumbnail":null,"size":761388},{"id":"8f107581-3ab8-4834-8219-545f3814c008","file":"DSC_8887.jpg","width":"1053","height":"1600","date":"2023:09:30 16:59:26","thumbnail":null,"size":613389},{"id":"ee53e40d-5338-4448-8255-3aa6452aeb52","file":"DSC_8885.jpg","width":"1053","height":"1600","date":"2023:09:30 16:58:13","thumbnail":null,"size":473044},{"id":"aaab4321-5bf3-4f52-9060-a4745ff618ee","file":"DSC_8886.jpg","width":"1053","height":"1600","date":"2023:09:30 16:58:13","thumbnail":null,"size":462288},{"id":"6f268a84-e625-442d-a0cc-b497389e431b","file":"DSC_8883.jpg","width":"1053","height":"1600","date":"2023:09:30 16:58:12","thumbnail":null,"size":463405},{"id":"63b279ab-17e2-4bd8-ab1e-2ce901979eff","file":"DSC_8884.jpg","width":"1053","height":"1600","date":"2023:09:30 16:58:12","thumbnail":null,"size":469623},{"id":"001b9bce-20d8-4182-a7b7-59346c87fec6","file":"DSC_8882.jpg","width":"1053","height":"1600","date":"2023:09:30 16:58:11","thumbnail":null,"size":456047},{"id":"1eec5102-b5fe-457d-9ed0-72efe79b3536","file":"DSC_8880.jpg","width":"1053","height":"1600","date":"2023:09:30 16:57:51","thumbnail":null,"size":555640},{"id":"bc0ba3b9-a3d9-48f2-9398-b0b28a969c16","file":"DSC_8881.jpg","width":"1053","height":"1600","date":"2023:09:30 16:57:51","thumbnail":null,"size":549561},{"id":"73376b8a-4d7a-486b-a769-f86f94ad92c0","file":"DSC_8879.jpg","width":"1053","height":"1600","date":"2023:09:30 16:57:50","thumbnail":null,"size":575652},{"id":"8f48593b-d6d6-41fc-be45-64698de3d022","file":"DSC_8878.jpg","width":"1053","height":"1600","date":"2023:09:30 16:57:46","thumbnail":null,"size":461319},{"id":"7f8a1bdb-07f9-411a-a520-e57a569d5bbb","file":"DSC_8877.jpg","width":"1053","height":"1600","date":"2023:09:30 16:57:43","thumbnail":null,"size":442276},{"id":"19f31c52-d090-4dde-89d3-95d768aaa1a5","file":"DSC_8876.jpg","width":"1053","height":"1600","date":"2023:09:30 16:57:38","thumbnail":null,"size":386792},{"id":"1a2c6a4d-d55f-4659-90ed-205c4d1a394a","file":"DSC_8875.jpg","width":"1053","height":"1600","date":"2023:09:30 16:57:28","thumbnail":null,"size":387623},{"id":"7d17b1cd-6de0-4d50-8b17-f87c8f4d2a46","file":"DSC_8874.jpg","width":"1053","height":"1600","date":"2023:09:30 16:57:23","thumbnail":null,"size":421423},{"id":"5cfe99eb-44fb-410b-b47f-dc61bcfa3712","file":"DSC_8872.jpg","width":"1053","height":"1600","date":"2023:09:30 16:57:19","thumbnail":null,"size":408269},{"id":"55d1fdd9-7503-4c96-83d2-22feaf2ea590","file":"DSC_8873.jpg","width":"1053","height":"1600","date":"2023:09:30 16:57:19","thumbnail":null,"size":385841},{"id":"064c287f-c882-4139-8f87-c936d550167e","file":"DSC_8870.jpg","width":"1053","height":"1600","date":"2023:09:30 16:57:05","thumbnail":null,"size":428380},{"id":"41196b92-573f-4fb1-ae4c-407d35ce81e3","file":"DSC_8871.jpg","width":"1053","height":"1600","date":"2023:09:30 16:57:05","thumbnail":null,"size":428935},{"id":"a77d020c-e7a8-4d85-91f3-9ac009458f9e","file":"DSC_8869.jpg","width":"1053","height":"1600","date":"2023:09:30 16:57:03","thumbnail":null,"size":414375},{"id":"8bfef1e5-aa6d-421f-a0f9-29f48c647652","file":"DSC_8868.jpg","width":"1053","height":"1600","date":"2023:09:30 16:56:54","thumbnail":null,"size":525883},{"id":"85dbd5c2-6619-4deb-a558-ca1683892756","file":"DSC_8867.jpg","width":"1053","height":"1600","date":"2023:09:30 16:56:49","thumbnail":null,"size":509766},{"id":"46e07ffb-c533-4b3e-b78e-05ca66376d2c","file":"DSC_8866.jpg","width":"1053","height":"1600","date":"2023:09:30 16:56:48","thumbnail":null,"size":425542},{"id":"e7b80c69-c389-4b60-bc12-97df43a843c5","file":"DSC_8865.jpg","width":"1053","height":"1600","date":"2023:09:30 16:56:31","thumbnail":null,"size":264781},{"id":"29a30061-611f-4100-b26b-512dfcb497fe","file":"DSC_8864.jpg","width":"1053","height":"1600","date":"2023:09:30 16:56:30","thumbnail":null,"size":267444},{"id":"3f4b1e4e-1baa-43aa-8fe1-ad71d91961a5","file":"DSC_8863.jpg","width":"1053","height":"1600","date":"2023:09:30 16:56:29","thumbnail":null,"size":237566},{"id":"8c2eda8b-fdff-4eea-87be-e57753bc5b9c","file":"DSC_8862.jpg","width":"1053","height":"1600","date":"2023:09:30 16:56:23","thumbnail":null,"size":274108},{"id":"4e330c7d-c6b4-453d-9c8a-33178d3ed6e5","file":"DSC_8860.jpg","width":"1053","height":"1600","date":"2023:09:30 16:55:51","thumbnail":null,"size":316423},{"id":"77acb5c7-96b8-4aa0-a37d-afdb3ae77ebc","file":"DSC_8859.jpg","width":"1053","height":"1600","date":"2023:09:30 16:55:50","thumbnail":null,"size":336755},{"id":"83d4cd29-3140-4b84-8687-794f2ac9e979","file":"DSC_8858.jpg","width":"1053","height":"1600","date":"2023:09:30 16:55:46","thumbnail":null,"size":307975},{"id":"f17680c9-5847-4f7e-926f-790b319af571","file":"DSC_8857.jpg","width":"2432","height":"1600","date":"2023:09:30 16:55:37","thumbnail":null,"size":310237},{"id":"0f2bb44d-d881-43b4-a221-cfda2d825cee","file":"DSC_8856.jpg","width":"2432","height":"1600","date":"2023:09:30 16:55:35","thumbnail":null,"size":316307}],"image_count":345,"video_count":0,"heic_count":0,"youtube_count":0}},"image_count":345,"size":172279187,"video_count":0,"youtube_count":0,"directory_info":{"directory":"346M","git":"157M","thumbnails":"25M","folders":[{"size":"166M","name":"images","storage_path":"\/mnt\/TOSHIBA-DATA2\/khieu-ngoan-git\/tanaka-20231020-p2\/images"}]}}